Workbook

Sheet README
A1: Last Updated: May 01, 2026 04:35 AM | B1: 2026-06-23 11:45 EDT
A2: Total Deals in RFP Data: 652
A3: Total Awards: 81
A4: Source: HubSpot CRM (live pull)
A5: Agency State: sourced from associated Company object agency_state property
A6: Total Records: | B6: 775

Sheet Summary
A1: CAPS RFP DASHBOARD - SUMMARY
A2: Last Refreshed: April 23, 2026
A4: OVERVIEW METRICS
A5: Total RFPs | B5: =COUNTA('RFP Data'!A2:A687)
A6: RFPs with Amount | B6: =COUNTA('RFP Data'!L2:L687)
A7: Total Pipeline Value | B7: =SUM('RFP Data'!L2:L687)
A8: Average Deal Size | B8: =IF(B6>0,B7/B6,0)
A10: INTERVIEW METRICS
A11: Total Deals with Interviews | B11: =COUNTIF('RFP Data'!H2:H687,"Yes") | D11: Subcategory: Interview | E11: =COUNTIF('RFP Data'!I2:I687,"Interview")
A12: Interview Rate (of Total) | B12: =IF(B5>0,B11/B5,0) | D12: Subcategory: BAFO | E12: =COUNTIF('RFP Data'!I2:I687,"BAFO")
A14: AWARD TIMELINE METRICS
A15: Deals with Intent to Award Date | B15: =COUNTA('RFP Data'!S2:S687) | D15: Intent to Award Value ($) | E15: =SUMPRODUCT(('RFP Data'!S2:S687<>"")*1,'RFP Data'!L2:L687)
A16: Deals with Tentatively Awarded Date | B16: =COUNTA('RFP Data'!T2:T687)
A17: Deals with Awarded Date | B17: =COUNTA('RFP Data'!U2:U687) | D17: Awarded Value ($) | E17: =SUMPRODUCT(('RFP Data'!U2:U687<>"")*1,'RFP Data'!L2:L687)
A20: BY STAGE
A21: Stage | B21: Count | D21: Stage | E21: Total Value ($)
A22: Submitted | B22: =COUNTIF('RFP Data'!G2:G687,A22) | D22: Submitted | E22: =SUMIF('RFP Data'!G2:G687,D22,'RFP Data'!L2:L687)
A23: Interview | B23: =COUNTIF('RFP Data'!G2:G687,A23) | D23: Interview | E23: =SUMIF('RFP Data'!G2:G687,D23,'RFP Data'!L2:L687)
A24: Intent to Award | B24: =COUNTIF('RFP Data'!G2:G687,A24) | D24: Intent to Award | E24: =SUMIF('RFP Data'!G2:G687,D24,'RFP Data'!L2:L687)
A25: Closed Won | B25: =COUNTIF('RFP Data'!G2:G687,A25) | D25: Closed Won | E25: =SUMIF('RFP Data'!G2:G687,D25,'RFP Data'!L2:L687)
A26: Closed Lost | B26: =COUNTIF('RFP Data'!G2:G687,A26) | D26: Closed Lost | E26: =SUMIF('RFP Data'!G2:G687,D26,'RFP Data'!L2:L687)
A27: Terminated | B27: =COUNTIF('RFP Data'!G2:G687,A27) | D27: Terminated | E27: =SUMIF('RFP Data'!G2:G687,D27,'RFP Data'!L2:L687)
A28: RFx Cancelled | B28: =COUNTIF('RFP Data'!G2:G687,A28) | D28: RFx Cancelled | E28: =SUMIF('RFP Data'!G2:G687,D28,'RFP Data'!L2:L687)
A31: BY OWNER
A32: Owner | B32: Count | D32: Owner | E32: Total Value ($)
A33: Ashutosh Chauhan | B33: =COUNTIF('RFP Data'!O2:O687,A33) | D33: Ashutosh Chauhan | E33: =SUMIF('RFP Data'!O2:O687,D33,'RFP Data'!L2:L687)
A34: Jyothsna Nanda kishore | B34: =COUNTIF('RFP Data'!O2:O687,A34) | D34: Jyothsna Nanda kishore | E34: =SUMIF('RFP Data'!O2:O687,D34,'RFP Data'!L2:L687)
A35: Abhishek Zalani | B35: =COUNTIF('RFP Data'!O2:O687,A35) | D35: Abhishek Zalani | E35: =SUMIF('RFP Data'!O2:O687,D35,'RFP Data'!L2:L687)
A36: Savya Atrey | B36: =COUNTIF('RFP Data'!O2:O687,A36) | D36: Savya Atrey | E36: =SUMIF('RFP Data'!O2:O687,D36,'RFP Data'!L2:L687)
A37: Madhav Mitruka | B37: =COUNTIF('RFP Data'!O2:O687,A37) | D37: Madhav Mitruka | E37: =SUMIF('RFP Data'!O2:O687,D37,'RFP Data'!L2:L687)
A38: Arshdeep Kaur | B38: =COUNTIF('RFP Data'!O2:O687,A38) | D38: Arshdeep Kaur | E38: =SUMIF('RFP Data'!O2:O687,D38,'RFP Data'!L2:L687)
A39: Vinay Srinivasan | B39: =COUNTIF('RFP Data'!O2:O687,A39) | D39: Vinay Srinivasan | E39: =SUMIF('RFP Data'!O2:O687,D39,'RFP Data'!L2:L687)
A40: Ritoban Maitra | B40: =COUNTIF('RFP Data'!O2:O687,A40) | D40: Ritoban Maitra | E40: =SUMIF('RFP Data'!O2:O687,D40,'RFP Data'!L2:L687)
A41: Ashley Lamaniya | B41: =COUNTIF('RFP Data'!O2:O687,A41) | D41: Ashley Lamaniya | E41: =SUMIF('RFP Data'!O2:O687,D41,'RFP Data'!L2:L687)
A42: Hrithik Srivastava | B42: =COUNTIF('RFP Data'!O2:O687,A42) | D42: Hrithik Srivastava | E42: =SUMIF('RFP Data'!O2:O687,D42,'RFP Data'!L2:L687)
A45: BY SERVICE CATEGORY
A46: Category | B46: Count | D46: Category | E46: Total Value ($)
A47: Managed Services (MSP) | B47: =COUNTIF('RFP Data'!M2:M687,"*"&A47&"*") | D47: Managed Services (MSP) | E47: =SUMIF('RFP Data'!M2:M687,"*"&D47&"*",'RFP Data'!L2:L687)
A48: Consulting | B48: =COUNTIF('RFP Data'!M2:M687,"*"&A48&"*") | D48: Consulting | E48: =SUMIF('RFP Data'!M2:M687,"*"&D48&"*",'RFP Data'!L2:L687)
A49: Platform Implementation (ERP, CRMs) | B49: =COUNTIF('RFP Data'!M2:M687,"*"&A49&"*") | D49: Platform Implementation (ERP, CRMs) | E49: =SUMIF('RFP Data'!M2:M687,"*"&D49&"*",'RFP Data'!L2:L687)
A50: Staff Augmentation | B50: =COUNTIF('RFP Data'!M2:M687,"*"&A50&"*") | D50: Staff Augmentation | E50: =SUMIF('RFP Data'!M2:M687,"*"&D50&"*",'RFP Data'!L2:L687)
A51: Reseller | B51: =COUNTIF('RFP Data'!M2:M687,"*"&A51&"*") | D51: Reseller | E51: =SUMIF('RFP Data'!M2:M687,"*"&D51&"*",'RFP Data'!L2:L687)
A52: Audits and Assessment | B52: =COUNTIF('RFP Data'!M2:M687,"*"&A52&"*") | D52: Audits and Assessment | E52: =SUMIF('RFP Data'!M2:M687,"*"&D52&"*",'RFP Data'!L2:L687)
A53: Modernization / Migration | B53: =COUNTIF('RFP Data'!M2:M687,"*"&A53&"*") | D53: Modernization / Migration | E53: =SUMIF('RFP Data'!M2:M687,"*"&D53&"*",'RFP Data'!L2:L687)
A54: Support & Maintenance | B54: =COUNTIF('RFP Data'!M2:M687,"*"&A54&"*") | D54: Support & Maintenance | E54: =SUMIF('RFP Data'!M2:M687,"*"&D54&"*",'RFP Data'!L2:L687)
A55: Training | B55: =COUNTIF('RFP Data'!M2:M687,"*"&A55&"*") | D55: Training | E55: =SUMIF('RFP Data'!M2:M687,"*"&D55&"*",'RFP Data'!L2:L687)
A58: WIN / LOSS METRICS
A59: Closed Won | B59: =COUNTIF('RFP Data'!G2:G687,"Closed Won") | D59: Closed Won Value | E59: =SUMIF('RFP Data'!G2:G687,"Closed Won",'RFP Data'!L2:L687)
A60: Closed Lost | B60: =COUNTIF('RFP Data'!G2:G687,"Closed Lost") | D60: Closed Lost Value | E60: =SUMIF('RFP Data'!G2:G687,"Closed Lost",'RFP Data'!L2:L687)
A61: Win Rate | B61: =IF((B59+B60)>0,B59/(B59+B60),0) | D61: Win Rate by Value | E61: =IF((E59+E60)>0,E59/(E59+E60),0)
A63: Won after Interview | B63: =COUNTIFS('RFP Data'!G2:G687,"Closed Won",'RFP Data'!H2:H687,"Yes")
A64: Lost after Interview | B64: =COUNTIFS('RFP Data'!G2:G687,"Closed Lost",'RFP Data'!H2:H687,"Yes")
A65: Interview-to-Win Rate | B65: =IF((B63+B64)>0,B63/(B63+B64),0)

Sheet Stage Legend
A1: Stage | B1: Description | C1: HubSpot Internal ID
A2: Submitted | B2: Bid has been submitted and is awaiting review | C2: presentationscheduled
A3: Interview | B3: Shortlisted for interview / BAFO stage | C3: 1620129473
A4: Intent to Award | B4: Agency has indicated intent to award | C4: 2485737153
A5: Closed Won | B5: Deal has been won | C5: closedwon
A6: Closed Lost | B6: Deal has been lost | C6: closedlost
A7: Terminated | B7: RFP process was terminated by the agency | C7: 2203296493
A8: RFx Cancelled | B8: RFP was cancelled before completion | C8: 2766010076
A11: Interview Subcategories
A12: Interview | B12: Standard interview — presentation, Q&A, demo
A13: BAFO | B13: Best and Final Offer — revised/final proposal requested
A15: Award Timeline
A16: Intent to Award Date | B16: Agency communicates intent to award — not yet official
A17: Tentatively Awarded Date | B17: Tentative/conditional award — may be subject to protest period
A18: Awarded Date | B18: Formal award — contract execution can begin

Sheet RFP Data
A1: S.No. | B1: HubSpot ID | C1: RFP Number | D1: Deal Name | E1: Agency | F1: Agency State | G1: Stage | H1: Interview Flag | I1: Interview Subcategory | J1: Bid Closing Date | K1: Submission Date | L1: Amount ($) | M1: Service Category | N1: Submission Mode | O1: Owner | P1: Interview Type | Q1: Interview Date | R1: BAFO Date | S1: Intent to Award Date | T1: Tentatively Awarded Date | U1: Awarded Date | V1: Award Status | W1: Won Reason | X1: Lost Reason | Y1: Created Date | Z1: HubSpot Link | AA1: Delivery Required
A2: 1 | B2: 180942918364 | D2: CITY WEBSITE REPLACEMENT PLATFORM | E2: City of Englewood | F2: Colorado | G2: Closed Lost | H2: No | J2: 45938 | K2: 45680 | M2: Modernization / Migration | O2: Madhav Mitruka | Y2: 2025-10-08 | Z2: https://app.hubspot.com/contacts/243046792/record/0-3/180942918364
A3: 2 | B3: 235860602564 | C3: RFQ-AR-1398 | D3: Metropolitan Water District of Southern California - On-Call Information Technology Cybersecurity Services | E3: Metropolitan Water District of Southern California | F3: California | G3: Closed Won | H3: No | J3: 45999 | K3: 45771 | M3: Managed Services (MSP) | N3: Portal | O3: Madhav Mitruka | S3: 2025-12-02 | U3: 45993 | Y3: 2025-12-08 | Z3: https://app.hubspot.com/contacts/243046792/record/0-3/235860602564
A4: 3 | B4: 127482765035 | C4: RFP NO. NC- 2025-14 | D4: Fresno County Superintendent of Schools - Computer Maintenance & Technology Support Services | E4: FRESNO COUNTY SUPERINTENDENT OF SCHOOLS | F4: California | G4: Closed Won | H4: No | J4: 45796 | K4: 45796 | L4: 500000 | M4: Consulting;Support & Maintenance | N4: Email | O4: Arshdeep Kaur | S4: 2025-06-13 | U4: 45968 | V4: In Process | Y4: 2025-07-23 | Z4: https://app.hubspot.com/contacts/243046792/record/0-3/127482765035 | AA4: No
A5: 4 | B5: 127743477490 | D5: EPIC 6- RFP 21.25 Technology Solutions & Services | E5: Region 6 Education Service Center | F5: Texas | G5: Closed Won | H5: No | J5: 46142 | K5: 45807 | M5: Staff Augmentation | N5: Portal | O5: Jyothsna Nanda kishore | S5: 2025-06-16 | U5: 45831 | Y5: 2025-07-23 | Z5: https://app.hubspot.com/contacts/243046792/record/0-3/127743477490 | AA5: No
A6: 5 | B6: 175110048474 | D6: Commonwealth of Pennsylvania - Agile ITQ Development | E6: Commonwealth of Pennsylvania | F6: Pennsylvania | G6: Closed Won | H6: No | J6: 45932 | K6: 45832 | M6: Staff Augmentation | N6: Portal | O6: Madhav Mitruka | S6: 2025-10-02 | U6: 45932 | Y6: 2025-10-02 | Z6: https://app.hubspot.com/contacts/243046792/record/0-3/175110048474 | AA6: No
A7: 6 | B7: 106496879328 | C7: 928 | D7: Cybersecurity & Information Security Services | G7: Closed Lost | H7: No | J7: 46112 | K7: 45834 | O7: Madhav Mitruka | Y7: 2025-06-25 | Z7: https://app.hubspot.com/contacts/243046792/record/0-3/106496879328
A8: 7 | B8: 121105638127 | C8: 25-0212-IT | D8: MICROSOFT OFFICE 365, EXCHANGE,DEFENDER, TRAINING AND TECH SUPPORT | E8: City of Florissant | F8: Missouri | G8: Closed Lost | H8: No | J8: 46113 | K8: 45835 | M8: Consulting | O8: Jyothsna Nanda kishore | V8: In Process | Y8: 2025-07-17 | Z8: https://app.hubspot.com/contacts/243046792/record/0-3/121105638127 | AA8: Yes
A9: 8 | B9: 110969525953 | C9: NA | D9: Managed IT Services - Lucas County | E9: Lucas County Board of Developmental Disabilities | F9: Ohio | G9: Closed Lost | H9: No | J9: 46113 | K9: 45841 | L9: 381250 | M9: Managed Services (MSP) | N9: Portal | O9: Jyothsna Nanda kishore | Y9: 2025-07-02 | Z9: https://app.hubspot.com/contacts/243046792/record/0-3/110969525953
A10: 9 | B10: 135153706705 | C10: RFQ1762822 | D10: Implementation of Electronic Filing (eFiling) | E10: U.S. Consumer Product Safety Commission (CPSC) | F10: Washington, D.C. | G10: Closed Lost | H10: No | J10: 46106 | K10: 45845 | M10: Platform Implementation (ERP, CRMs) | O10: Jyothsna Nanda kishore | Y10: 2025-07-31 | Z10: https://app.hubspot.com/contacts/243046792/record/0-3/135153706705
A11: 10 | B11: 119087249139 | D11: Enterprise Private Cloud Disaster Recovery Services | E11: Contra Costa County | F11: California | G11: Closed Lost | H11: Yes | I11: Interview | J11: 46146 | K11: 45848 | L11: 290000 | M11: Consulting | N11: Email | O11: Jyothsna Nanda kishore | P11: Interview Scheduled | Q11: 2025-09-18 | Y11: 2025-07-11 | Z11: https://app.hubspot.com/contacts/243046792/record/0-3/119087249139
A12: 11 | B12: 118951637707 | C12: RFP_F_0000000055 | D12: CRM ROADMAP: DISCOVERY & PHASE 1 IMPLEMTATION | E12: University of Colorado | F12: Colorado | G12: Closed Lost | H12: No | J12: 45975 | K12: 45852 | L12: 254000 | O12: Jyothsna Nanda kishore | Y12: 2025-07-11 | Z12: https://app.hubspot.com/contacts/243046792/record/0-3/118951637707
A13: 12 | B13: 110968805088 | C13: C001203 | D13: Senior Java Architect | E13: New York State Office of the State Comptroller | F13: New York | G13: Closed Lost | H13: No | J13: 46113 | K13: 45854 | M13: Staff Augmentation | N13: Email | O13: Jyothsna Nanda kishore | Y13: 2025-07-02 | Z13: https://app.hubspot.com/contacts/243046792/record/0-3/110968805088
A14: 13 | B14: 110968874738 | C14: 2025-019 | D14: (ERP) Tyler Software Configuration & Customization Services- QSL | G14: Closed Lost | H14: No | J14: 45937 | K14: 45859 | N14: Portal | O14: Madhav Mitruka | Y14: 2025-07-03 | Z14: https://app.hubspot.com/contacts/243046792/record/0-3/110968874738
A15: 14 | B15: 110712028891 | D15: Oregon League of Cities - STAFFING SERVICES WITH RELATED SERVICES AND SOLUTIONS | E15: Oregon League of Cities | F15: Oregon | G15: Closed Won | H15: No | J15: 46007 | K15: 45859 | M15: Staff Augmentation | N15: Portal | O15: Madhav Mitruka | S15: 2025-12-15 | U15: 46066 | Y15: 2025-07-01 | Z15: https://app.hubspot.com/contacts/243046792/record/0-3/110712028891 | AA15: Yes
A16: 15 | B16: 110968803016 | C16: RFQ-0011580-TECH-2025 | D16: Power Platform/Azure Fabric Launch RFQ | G16: Closed Lost | H16: No | J16: 45936 | K16: 45860 | M16: Consulting | N16: Portal | O16: Madhav Mitruka | Y16: 2025-07-02 | Z16: https://app.hubspot.com/contacts/243046792/record/0-3/110968803016
A17: 16 | B17: 127424133880 | C17: 5400028271 | D17: State of South Carolina - STC Dynamics Managed Service Provider | E17: State of South Carolina | F17: South Carolina | G17: Closed Won | H17: No | J17: 45971 | K17: 45860 | M17: Managed Services (MSP);Staff Augmentation | N17: Email | O17: Jyothsna Nanda kishore | S17: 2025-11-06 | U17: 45967 | Y17: 2025-07-22 | Z17: https://app.hubspot.com/contacts/243046792/record/0-3/127424133880 | AA17: Yes
A18: 17 | B18: 114864544502 | D18: University System of New Hampshire - Workday Related Staff Augmentation and Project Work | E18: University System of New Hampshire | F18: New Hampshire | G18: Closed Won | H18: No | J18: 45981 | K18: 45861 | M18: Staff Augmentation | N18: Portal | O18: Madhav Mitruka | S18: 2025-11-20 | U18: 46009 | Y18: 2025-07-08 | Z18: https://app.hubspot.com/contacts/243046792/record/0-3/114864544502
A19: 18 | B19: 114864633585 | D19: IT Services | E19: Midway City Corporation | F19: Utah | G19: Closed Lost | H19: No | J19: 45943 | K19: 45866 | L19: 130560 | N19: Email | O19: Madhav Mitruka | Y19: 2025-07-09 | Z19: https://app.hubspot.com/contacts/243046792/record/0-3/114864633585
A20: 19 | B20: 114864655035 | D20: IT CYBERSECURITY MANAGED SERVICES | E20: Clark Township | F20: New Jersey | G20: Closed Lost | H20: No | J20: 45943 | K20: 45867 | L20: 444440 | M20: Managed Services (MSP) | N20: Offline | O20: Madhav Mitruka | Y20: 2025-07-09 | Z20: https://app.hubspot.com/contacts/243046792/record/0-3/114864655035
A21: 20 | B21: 115653873387 | D21: Implementation Services for Microsoft Power Platform Solution for NYS Department of Health’s Temporary Healthcare Staffing Agency Registration System | E21: New York State Department of Health | F21: New York | G21: Closed Lost | H21: No | J21: 45936 | K21: 45868 | L21: 111000 | M21: Platform Implementation (ERP, CRMs) | N21: Email | O21: Madhav Mitruka | Y21: 2025-07-07 | Z21: https://app.hubspot.com/contacts/243046792/record/0-3/115653873387
A22: 21 | B22: 134586521300 | D22: SMUD.org Software and Technical Infrastructure Upgrade | E22: Sacramento Municipal Utility District | F22: California | G22: Closed Lost | H22: No | J22: 45975 | K22: 45868 | O22: Jyothsna Nanda kishore | Y22: 2025-07-31 | Z22: https://app.hubspot.com/contacts/243046792/record/0-3/134586521300
A23: 22 | B23: 110968802000 | C23: 201-2025-1000-1 | D23: School Data Migration | E23: North Dakota Department of Public Instruction | F23: North Dakota | G23: Terminated | H23: No | J23: 46154 | K23: 45868 | L23: 193000 | M23: Modernization / Migration | N23: Portal | O23: Arshdeep Kaur | Y23: 2025-07-02 | Z23: https://app.hubspot.com/contacts/243046792/record/0-3/110968802000 | AA23: Yes
A24: 23 | B24: 121105455817 | D24: MSSP | E24: City of Aurora | F24: Illinois | G24: Closed Lost | H24: No | J24: 45947 | K24: 45875 | L24: 4000000 | N24: Portal | O24: Madhav Mitruka | Y24: 2025-07-15 | Z24: https://app.hubspot.com/contacts/243046792/record/0-3/121105455817
A25: 24 | B25: 123259080428 | C25: 26-08-09 | D25: [Destroyed] Cybersecurity Pilot - Privileged Access Management (Pam) | E25: Weslaco ISD | F25: Texas | G25: Closed Lost | H25: No | J25: 45964 | K25: 45876 | L25: 34800 | M25: Managed Services (MSP) | N25: Portal | O25: Jyothsna Nanda kishore | Y25: 2025-07-18 | Z25: https://app.hubspot.com/contacts/243046792/record/0-3/123259080428
A26: 25 | B26: 122926380739 | D26: Clark County- Managed IT Services | E26: Clark County Sheriff's Office | F26: Ohio | G26: Closed Lost | H26: No | J26: 45975 | K26: 45876 | O26: Jyothsna Nanda kishore | Y26: 2025-07-18 | Z26: https://app.hubspot.com/contacts/243046792/record/0-3/122926380739
A27: 26 | B27: 114864545523 | C27: 25-003QP | D27: 25-003QP-Accela Business Systems Analysis | E27: City of Seattle | F27: Washington | G27: Closed Lost | H27: Yes | I27: Interview | J27: 45999 | K27: 45876 | L27: 477043 | M27: Consulting;Staff Augmentation | N27: Portal | O27: Ashutosh Chauhan | P27: Interview Scheduled | Q27: 2025-11-05 | Y27: 2025-07-08 | Z27: https://app.hubspot.com/contacts/243046792/record/0-3/114864545523
A28: 27 | B28: 120592685811 | C28: RFQ-1001295 | D28: Iowa State University - Cybersecurity Services for Iowa Political Subdivisions | E28: Iowa State University | F28: Iowa | G28: Closed Won | H28: No | J28: 45981 | K28: 45877 | M28: Audits and Assessment | N28: Portal | O28: Jyothsna Nanda kishore | S28: 2025-11-20 | U28: 46156 | Y28: 2025-07-15 | Z28: https://app.hubspot.com/contacts/243046792/record/0-3/120592685811 | AA28: Yes
A29: 28 | B29: 132776618729 | C29: IT-26-002 | D29: IT Professional Services - Laguna Beach | E29: Laguna Beach | F29: California | G29: Closed Lost | H29: No | J29: 45943 | K29: 45880 | M29: Managed Services (MSP) | N29: Portal | O29: Madhav Mitruka | Y29: 2025-07-29 | Z29: https://app.hubspot.com/contacts/243046792/record/0-3/132776618729
A30: 29 | B30: 114864632540 | D30: LP&L Oracle Utility Systems Support and Optimization Services | E30: Lubbock Power & Light | F30: Texas | G30: Closed Lost | H30: No | J30: 45943 | K30: 45881 | L30: 288000 | N30: Portal | O30: Madhav Mitruka | Y30: 2025-07-09 | Z30: https://app.hubspot.com/contacts/243046792/record/0-3/114864632540
A31: 30 | B31: 135506178796 | C31: RFP No: 7-30-25 | D31: Virtual CISO Services, HCCC Mountain Line, New Jersey | E31: Hudson County Community College | F31: New Jersey | G31: Closed Lost | H31: No | J31: 45960 | K31: 45882 | L31: 236100 | M31: Managed Services (MSP) | N31: Offline | O31: Jyothsna Nanda kishore | Y31: 2025-08-01 | Z31: https://app.hubspot.com/contacts/243046792/record/0-3/135506178796
A32: 31 | B32: 137470794434 | C32: BD-26-1274-TAOFF-TAOFF-119023 | D32: RFP - IT Support Services | E32: TOWN OF GRAFTON, OFFICE OF THE TOWN ADMINISTRATOR | F32: Massachusetts | G32: Closed Lost | H32: No | J32: 45975 | K32: 45885 | O32: Jyothsna Nanda kishore | Y32: 2025-08-06 | Z32: https://app.hubspot.com/contacts/243046792/record/0-3/137470794434
A33: 32 | B33: 129524913852 | C33: 2124952 | D33: Broadcom CA ESP dSeries Workload Automation Migration | E33: New York State Office of the State Comptroller | F33: New York | G33: Closed Lost | H33: Yes | I33: Interview | J33: 46182 | K33: 45887 | L33: 126200 | M33: Modernization / Migration | N33: Email | O33: Madhav Mitruka | P33: Interview Scheduled | Q33: 2025-10-23 | Y33: 2025-07-28 | Z33: https://app.hubspot.com/contacts/243046792/record/0-3/129524913852 | AA33: Yes
A34: 33 | B34: 122926374597 | D34: Managed IT Services | E34: City of Sultan | F34: Washington | G34: Closed Lost | H34: Yes | I34: Interview | J34: 45999 | K34: 45889 | M34: Managed Services (MSP) | O34: Madhav Mitruka | P34: Interview Scheduled | Q34: 2025-09-17 | Y34: 2025-07-18 | Z34: https://app.hubspot.com/contacts/243046792/record/0-3/122926374597
A35: 34 | B35: 137207253716 | C35: SRC0000032957 | D35: Peoplesoft Managed Services | E35: Ohio Department of Taxation | F35: Ohio | G35: Closed Lost | H35: No | J35: 45960 | K35: 45890 | L35: 47400 | M35: Managed Services (MSP) | N35: Portal | O35: Madhav Mitruka | Y35: 2025-08-06 | Z35: https://app.hubspot.com/contacts/243046792/record/0-3/137207253716
A36: 35 | B36: 142119196407 | D36: Information Technology Consulting and Support| Tahoe | E36: Tahoe Transportation District | F36: Nevada | G36: Closed Lost | H36: No | J36: 45936 | K36: 45891 | L36: 318549 | M36: Managed Services (MSP) | O36: Madhav Mitruka | Y36: 2025-08-14 | Z36: https://app.hubspot.com/contacts/243046792/record/0-3/142119196407
A37: 36 | B37: 137470794439 | C37: ITS-001-26 | D37: HIPAA Privacy & Security Assessment | E37: Boston Public Health Commission | F37: Massachusetts | G37: Closed Lost | H37: No | J37: 45972 | K37: 45891 | L37: 56300 | M37: Consulting | N37: Email | O37: Jyothsna Nanda kishore | Y37: 2025-08-06 | Z37: https://app.hubspot.com/contacts/243046792/record/0-3/137470794439
A38: 37 | B38: 141008904946 | C38: AD-25-RFP-2027 | D38: IT Outsourced Help Desk and Infrastructure | E38: Housing Authority of the City of New Haven d/b/a Elm City Communities (ECC) | F38: Connecticut | G38: Closed Lost | H38: Yes | I38: Interview | J38: 45979 | K38: 45891 | L38: 3200000 | N38: Portal | O38: Madhav Mitruka | P38: Interview Scheduled | Q38: 2025-10-16 | Y38: 2025-08-13 | Z38: https://app.hubspot.com/contacts/243046792/record/0-3/141008904946
A39: 38 | B39: 135506180801 | C39: RFP 25-HR-001 | D39: HR Civil Service Records Management System | E39: County of Oswego | F39: New York | G39: Closed Lost | H39: No | J39: 45944 | K39: 45896 | L39: 320760 | N39: Portal | O39: Jyothsna Nanda kishore | Y39: 2025-08-01 | Z39: https://app.hubspot.com/contacts/243046792/record/0-3/135506180801
A40: 39 | B40: 137815198453 | C40: RFP No. FIN0825-001 | D40: Municipal Water District of Orange County (MWDOC) Enterprise Planning Resource (ERP) System Architecture and Configuration (RFP No. FIN0825-001) | E40: Municipal Water District of Orange County (MWDOC) | F40: California | G40: Closed Won | H40: Yes | I40: Interview | J40: 45936 | K40: 45905 | L40: 90000 | M40: Platform Implementation (ERP, CRMs) | N40: Email | O40: Madhav Mitruka | P40: Interview Scheduled | Q40: 2025-09-17 | S40: 2025-10-13 | U40: 45972 | V40: In Process | Y40: 2025-08-06 | Z40: https://app.hubspot.com/contacts/243046792/record/0-3/137815198453 | AA40: Yes
A41: 40 | B41: 140837167831 | C41: PCS25-004RFP | D41: Workday Student Implementation Project Support Portland Community College | E41: Portland Community College | F41: Oregon | G41: RFx Cancelled | H41: No | J41: 46031 | K41: 45905 | L41: 278144 | M41: Platform Implementation (ERP, CRMs) | N41: Portal | O41: Jyothsna Nanda kishore | Y41: 2025-08-12 | Z41: https://app.hubspot.com/contacts/243046792/record/0-3/140837167831
A42: 41 | B42: 144659633851 | C42: RFQ1777899S | D42: REISSED- G0014 Enterprise Service Bus (ESB) Integration Modernization Project | E42: New York City Department of Education (NYCDOE) | F42: New York | G42: Closed Lost | H42: No | J42: 46163 | K42: 45908 | N42: Email | O42: Madhav Mitruka | Y42: 2025-08-22 | Z42: https://app.hubspot.com/contacts/243046792/record/0-3/144659633851
A43: 42 | B43: 155752318681 | C43: 2026-018 | D43: RFP 2026-018 VMware Managed Services | E43: University of Maine System | F43: Maine | G43: Closed Lost | H43: No | J43: 45975 | K43: 45911 | O43: Jyothsna Nanda kishore | Y43: 2025-09-04 | Z43: https://app.hubspot.com/contacts/243046792/record/0-3/155752318681
A44: 43 | B44: 142160624331 | C44: RFP194982 | D44: Customer Program Tracking and Management Platform | E44: City of Palo Alto | F44: California | G44: Closed Lost | H44: No | J44: 45993 | K44: 45911 | L44: 1095180 | M44: Platform Implementation (ERP, CRMs) | N44: Portal | O44: Ashutosh Chauhan | Y44: 2025-08-14 | Z44: https://app.hubspot.com/contacts/243046792/record/0-3/142160624331
A45: 44 | B45: 128661476072 | C45: 2025-RFP-003 | D45: Enterprise Database Management Software Solution | E45: Neoride | F45: Ohio | G45: Closed Lost | H45: No | J45: 45938 | K45: 45912 | L45: 385000 | M45: Managed Services (MSP) | N45: Portal | O45: Madhav Mitruka | Y45: 2025-07-24 | Z45: https://app.hubspot.com/contacts/243046792/record/0-3/128661476072
A46: 45 | B46: 145653736145 | D46: Information Technology Managed Services | E46: North Tahoe Public Utility District | F46: California | G46: Closed Lost | H46: No | J46: 45943 | K46: 45912 | M46: Managed Services (MSP) | N46: Email | O46: Madhav Mitruka | Y46: 2025-08-25 | Z46: https://app.hubspot.com/contacts/243046792/record/0-3/145653736145
A47: 46 | B47: 155021639360 | D47: IT and Cybersecurity | E47: City of Mary Esther | F47: Florida | G47: Closed Lost | H47: No | J47: 46001 | K47: 45912 | O47: Jyothsna Nanda kishore | Y47: 2025-09-03 | Z47: https://app.hubspot.com/contacts/243046792/record/0-3/155021639360
A48: 47 | B48: 140837204686 | D48: ERP Software Needs Analysis | E48: Town of Mooresville | F48: North Carolina | G48: Closed Lost | H48: No | J48: 46036 | K48: 45915 | M48: Consulting | O48: Madhav Mitruka | Y48: 2025-08-12 | Z48: https://app.hubspot.com/contacts/243046792/record/0-3/140837204686
A49: 48 | B49: 134489494217 | D49: Florida Department of Management Services - Prequalification for Information Technology Staff Augmentation Services (Supplemental) 2025 | E49: Florida Department of Management Services | F49: Florida | G49: Closed Won | H49: No | J49: 45932 | K49: 45916 | M49: Staff Augmentation | N49: Portal | O49: Madhav Mitruka | S49: 2025-09-16 | U49: 46049 | Y49: 2025-07-30 | Z49: https://app.hubspot.com/contacts/243046792/record/0-3/134489494217 | AA49: No
A50: 49 | B50: 137152430816 | C50: 25-551HDA-INFOT-B-48408 | D50: Managed Database Services | E50: Illinois Housing Development Authority | F50: Illinois | G50: Closed Lost | H50: No | J50: 45943 | K50: 45918 | L50: 800000 | N50: Portal | O50: Madhav Mitruka | Y50: 2025-08-05 | Z50: https://app.hubspot.com/contacts/243046792/record/0-3/137152430816
A51: 50 | B51: 156444965596 | D51: Update of Oracle PBCS for New Classification and Compensation Structure Integration | E51: City of Raleigh | F51: North Carolina | G51: RFx Cancelled | H51: No | J51: 45964 | K51: 45918 | N51: Email | O51: Jyothsna Nanda kishore | Y51: 2025-09-08 | Z51: https://app.hubspot.com/contacts/243046792/record/0-3/156444965596
A52: 51 | B52: 144653136611 | D52: Western Municipal Water District - Data Solution Design, Build & Implementation, Western Municipal Water District (Western Water) | E52: Western Municipal Water District | F52: California | G52: Closed Won | H52: No | J52: 46009 | K52: 45918 | L52: 143460 | M52: Modernization / Migration | N52: Portal | O52: Jyothsna Nanda kishore | S52: 2025-11-18 | U52: 45973 | V52: In Process | Y52: 2025-08-22 | Z52: https://app.hubspot.com/contacts/243046792/record/0-3/144653136611 | AA52: Yes
A53: 52 | B53: 141029722846 | C53: RFP_F-Contr-0000000117 | D53: Workday Managed Services | E53: Contra Costa County | F53: California | G53: Closed Lost | H53: No | J53: 46093 | K53: 45919 | L53: 192500 | M53: Managed Services (MSP) | N53: Portal | O53: Madhav Mitruka | Y53: 2025-08-12 | Z53: https://app.hubspot.com/contacts/243046792/record/0-3/141029722846
A54: 53 | B54: 159502266096 | C54: RFQ1771489 | D54: Airframe Forecasting Dashboard A.I. Tool | G54: Closed Lost | H54: No | J54: 45932 | K54: 45922 | L54: 52140 | O54: Madhav Mitruka | Y54: 2025-09-12 | Z54: https://app.hubspot.com/contacts/243046792/record/0-3/159502266096
A55: 54 | B55: 159420370672 | D55: Data Migration Services | E55: Huntington Park | F55: California | G55: Closed Lost | H55: No | J55: 45940 | K55: 45922 | L55: 40450 | M55: Modernization / Migration | O55: Madhav Mitruka | Y55: 2025-09-12 | Z55: https://app.hubspot.com/contacts/243046792/record/0-3/159420370672
A56: 55 | B56: 146982533875 | C56: RFP# 25-26-19 | D56: Information Technology (IT) Support Services | E56: City of Santa Clara | F56: California | G56: Closed Lost | H56: No | J56: 45943 | K56: 45922 | M56: Managed Services (MSP) | N56: Email | O56: Madhav Mitruka | Y56: 2025-08-28 | Z56: https://app.hubspot.com/contacts/243046792/record/0-3/146982533875
A57: 56 | B57: 144653137594 | D57: Web development and services Colorado Department of Natural Resources (CAIC) | E57: Colorado Avalanche Information Center (“CAIC”) (Department of Natural Resources) | F57: Colorado | G57: Closed Lost | H57: No | J57: 45964 | K57: 45923 | M57: Consulting;Platform Implementation (ERP, CRMs) | N57: Portal | O57: Jyothsna Nanda kishore | Y57: 2025-08-22 | Z57: https://app.hubspot.com/contacts/243046792/record/0-3/144653137594
A58: 57 | B58: 155514382045 | C58: Solicitation No: 226-15 | D58: SQL SERVER MANAGEMENT STUDIO (SSMS) PRODUCTIVITY AND DATABASE TOOLSET | E58: The School District of Greenville County (District) | F58: South Carolina | G58: RFx Cancelled | H58: No | J58: 45979 | K58: 45924 | M58: Platform Implementation (ERP, CRMs) | O58: Jyothsna Nanda kishore | Y58: 2025-09-04 | Z58: https://app.hubspot.com/contacts/243046792/record/0-3/155514382045
A59: 58 | B59: 159541459657 | C59: WSD001 | D59: County of Los Angeles Department of Public Works - Microsoft Power Platform Training | E59: County of Los Angeles Department of Public Works | F59: California | G59: Closed Won | H59: No | J59: 46114 | K59: 45925 | L59: 12000 | M59: Training | N59: Email | O59: Jyothsna Nanda kishore | S59: 2026-04-02 | U59: 46113 | Y59: 2025-09-12 | Z59: https://app.hubspot.com/contacts/243046792/record/0-3/159541459657 | AA59: Yes
A60: 59 | B60: 158113558258 | D60: TRIMET - Data Center Assessment and Risk Mitigation Strategy | E60: Tri-County Metropolitan Transportation District of Oregon | F60: Oregon | G60: Closed Won | H60: Yes | I60: BAFO | J60: 46143 | K60: 45929 | L60: 20893 | M60: Audits and Assessment | N60: Portal | O60: Ashutosh Chauhan | P60: BAFO | R60: 2025-10-15 | S60: 2025-10-20 | U60: 45953 | Y60: 2025-09-10 | Z60: https://app.hubspot.com/contacts/243046792/record/0-3/158113558258 | AA60: Yes
A61: 60 | B61: 159504441074 | D61: Managed IT, CITY OF BURKBURNETT, TEXAS | G61: Submitted | H61: No | J61: 45931 | K61: 45930 | L61: 563816 | M61: Managed Services (MSP) | N61: Offline | O61: Jyothsna Nanda kishore | Y61: 45912 | Z61: https://app.hubspot.com/contacts/243046792/record/0-3/159504441074
A62: 61 | B62: 164634450618 | D62: Development and Implementation of Comprehensive Data Governance Policy | E62: Wake County Public School System | F62: North Carolina | G62: Submitted | H62: No | J62: 45937 | K62: 45930 | M62: Training;Consulting | N62: Offline | O62: Jyothsna Nanda kishore | Y62: 2025-09-22 | Z62: https://app.hubspot.com/contacts/243046792/record/0-3/164634450618
A63: 62 | B63: 158775171781 | D63: PeopleSoft to Oracle Cloud Infrastructure (OCI) Migration Services | G63: Submitted | H63: No | J63: 45938 | K63: 45930 | M63: Modernization / Migration | O63: Jyothsna Nanda kishore | Y63: 2025-09-11 | Z63: https://app.hubspot.com/contacts/243046792/record/0-3/158775171781
A64: 63 | B64: 162089315038 | D64: MULTI-FACTOR AUTHENTICATION | E64: Hopkinton | F64: Rhode Island | G64: Closed Lost | H64: No | J64: 45946 | K64: 45930 | L64: 17936 | M64: Support & Maintenance | N64: Offline | O64: Madhav Mitruka | Y64: 2025-09-18 | Z64: https://app.hubspot.com/contacts/243046792/record/0-3/162089315038
A65: 64 | B65: 163873091282 | D65: MICROSOFT GOVERNMENT OFFICE 365 LICENSING AND MIGRATION OF THE TOWN’S EMAIL SERVICES FROM ITS CURRENT HOSTED EXCHANGE ENVIRONMENT | E65: Hopkinton | F65: Rhode Island | G65: Closed Lost | H65: No | J65: 45946 | K65: 45930 | L65: 23989.41 | M65: Modernization / Migration | N65: Offline | O65: Madhav Mitruka | Y65: 2025-09-18 | Z65: https://app.hubspot.com/contacts/243046792/record/0-3/163873091282
A66: 65 | B66: 169109642973 | C66: TS-25-17 | D66: VEEAM SOFTWARE SUPPORT AND MAINTENANCE RENEWAL | E66: THE CITY OF PEMBROKE PINES | F66: Florida | G66: Submitted | H66: No | J66: 45951 | K66: 45930 | L66: 93430 | M66: Reseller | N66: Portal | O66: Madhav Mitruka | Y66: 2025-09-24 | Z66: https://app.hubspot.com/contacts/243046792/record/0-3/169109642973
A67: 66 | B67: 168227148525 | D67: ENTERPRISE RESOURCE PLANNING CONSULTING SERVICES | E67: City of Gastonia | F67: North Carolina | G67: Closed Lost | H67: No | J67: 46007 | K67: 45930 | M67: Platform Implementation (ERP, CRMs) | N67: Email | O67: Ritoban Maitra | Y67: 2025-09-23 | Z67: https://app.hubspot.com/contacts/243046792/record/0-3/168227148525
A68: 67 | B68: 154541043431 | D68: CRM System | E68: City of Rosenberg | F68: Texas | G68: Closed Lost | H68: No | J68: 46114 | K68: 45930 | L68: 64900 | M68: Platform Implementation (ERP, CRMs) | N68: Portal | O68: Jyothsna Nanda kishore | Y68: 2025-09-03 | Z68: https://app.hubspot.com/contacts/243046792/record/0-3/154541043431
A69: 68 | B69: 146097902300 | C69: IT-26-004 | D69: Laguna Beach Information Technology Master Plan | E69: Laguna Beach | F69: California | G69: Submitted | H69: No | J69: 45931 | K69: 45931 | L69: 97000 | N69: Portal | O69: Abhishek Zalani | Y69: 2025-08-26 | Z69: https://app.hubspot.com/contacts/243046792/record/0-3/146097902300
A70: 69 | B70: 158454899438 | C70: 2453 | D70: Business Intelligence Program | E70: St. Johns County | F70: Florida | G70: Submitted | H70: No | J70: 45932 | K70: 45932 | L70: 4900 | M70: Consulting | N70: Email | O70: Abhishek Zalani | Y70: 2025-09-11 | Z70: https://app.hubspot.com/contacts/243046792/record/0-3/158454899438
A71: 70 | B71: 159420375799 | C71: 2025-11864 | D71: Temporary Service Provider Services as Required | E71: Port of Portland | F71: Oregon | G71: Submitted | H71: No | J71: 45933 | K71: 45932 | M71: Staff Augmentation | O71: Abhishek Zalani | Y71: 2025-09-12 | Z71: https://app.hubspot.com/contacts/243046792/record/0-3/159420375799
A72: 71 | B72: 126595998432 | C72: RFP-554-2025-0052-0-2025/AH | D72: Raleigh Durham Airport Authority (NC) - SharePoint Consultant | E72: Raleigh Durham Airport Authority [NC] | F72: North Carolina | G72: Intent to Award | H72: No | J72: 46052 | K72: 45932 | L72: 18830 | M72: Consulting | N72: Portal | O72: Madhav Mitruka | S72: 46052 | Y72: 2025-07-21 | Z72: https://app.hubspot.com/contacts/243046792/record/0-3/126595998432
A73: 72 | B73: 161660341982 | D73: Greene County - PROFESSIONAL CONSULTANT SERVICES | E73: Greene County | F73: New York | G73: Closed Won | H73: No | J73: 46143 | K73: 45932 | M73: Staff Augmentation | N73: Offline | O73: Arshdeep Kaur | S73: 2025-12-09 | U73: 46093 | Y73: 2025-09-17 | Z73: https://app.hubspot.com/contacts/243046792/record/0-3/161660341982 | AA73: No
A74: 73 | B74: 169109642977 | C74: 163973 | D74: CNE - Oracle EPM Implementation Partner | E74: Cherokee Nation Business | F74: Oklahoma | G74: Submitted | H74: No | J74: 45932 | K74: 45933 | L74: 155400 | M74: Platform Implementation (ERP, CRMs) | N74: Email | O74: Abhishek Zalani | Y74: 2025-09-24 | Z74: https://app.hubspot.com/contacts/243046792/record/0-3/169109642977
A75: 74 | B75: 157345533677 | D75: Customer Relationship Manager Platform- Wyoming | E75: Wyoming Retirement System | F75: Wyoming | G75: Submitted | H75: No | J75: 45933 | K75: 45933 | M75: Platform Implementation (ERP, CRMs) | N75: Portal | O75: Arshdeep Kaur | Y75: 2025-09-08 | Z75: https://app.hubspot.com/contacts/243046792/record/0-3/157345533677
A76: 75 | B76: 158191708863 | D76: Information Technology Services | E76: Pine City | F76: Minnesota | G76: Submitted | H76: No | J76: 45933 | K76: 45933 | L76: 43330 | M76: Managed Services (MSP) | N76: Email | O76: Abhishek Zalani | Y76: 2025-09-10 | Z76: https://app.hubspot.com/contacts/243046792/record/0-3/158191708863
A77: 76 | B77: 159626988233 | D77: IT Managed Services | E77: Impact Community Action | F77: Ohio | G77: Closed Lost | H77: No | J77: 46162 | K77: 45936 | L77: 396333.53 | M77: Managed Services (MSP) | N77: Email | O77: Jyothsna Nanda kishore | Y77: 2025-09-12 | Z77: https://app.hubspot.com/contacts/243046792/record/0-3/159626988233
A78: 77 | B78: 159420371644 | C78: OPENP-25-038 | D78: Technical Support for Oracle EBS | E78: Jacksonville Transportation Authority | F78: Florida | G78: Closed Lost | H78: No | J78: 45957 | K78: 45936 | M78: Managed Services (MSP) | N78: Portal | O78: Ashutosh Chauhan | Y78: 2025-09-12 | Z78: https://app.hubspot.com/contacts/243046792/record/0-3/159420371644
A79: 78 | B79: 158113559231 | D79: City of San Carlos - Legacy File Server Migration to SharePoint Modernization | E79: City of San Carlos | F79: California | G79: Closed Won | H79: Yes | I79: Interview | J79: 46149 | K79: 45936 | L79: 98000 | M79: Modernization / Migration | N79: Email | O79: Abhishek Zalani | P79: Interview Scheduled | Q79: 2025-12-10 | S79: 2026-01-01 | U79: 46031 | Y79: 2025-09-10 | Z79: https://app.hubspot.com/contacts/243046792/record/0-3/158113559231
A80: 79 | B80: 140837168873 | D80: SAP S/4HANA CONVERSION AND MIGRATION SERVICES | E80: San Diego Metropolitan Transit System | F80: California | G80: Closed Lost | H80: No | J80: 46293 | K80: 45937 | L80: 996800 | M80: Modernization / Migration | O80: Jyothsna Nanda kishore | Y80: 2025-08-12 | Z80: https://app.hubspot.com/contacts/243046792/record/0-3/140837168873
A81: 80 | B81: 167226060504 | D81: Information Technology Management Services | E81: Town of Swanzey | F81: New Hampshire | G81: Closed Lost | H81: No | J81: 46007 | K81: 45937 | L81: 66120 | M81: Managed Services (MSP) | N81: Offline | O81: Jyothsna Nanda kishore | Y81: 2025-09-22 | Z81: https://app.hubspot.com/contacts/243046792/record/0-3/167226060504
A82: 81 | B82: 167226058440 | C82: 186063 | D82: REQUEST FOR PROPOSAL 186063: Internal Audit Services | E82: City of Detroit | F82: Michigan | G82: Submitted | H82: No | J82: 45938 | K82: 45938 | L82: 46000 | M82: Audits and Assessment | N82: Portal | O82: Abhishek Zalani | Y82: 2025-09-22 | Z82: https://app.hubspot.com/contacts/243046792/record/0-3/167226058440
A83: 82 | B83: 163703775952 | D83: IT Consultant | E83: Dupage County | F83: Illinois | G83: Submitted | H83: No | J83: 45938 | K83: 45938 | M83: Staff Augmentation | O83: Arshdeep Kaur | Y83: 2025-09-18 | Z83: https://app.hubspot.com/contacts/243046792/record/0-3/163703775952
A84: 83 | B84: 180873330422 | D84: NuHarbor SOC | E84: California Department of State Hospitals | F84: California | G84: Submitted | H84: No | J84: 45938 | K84: 45939 | L84: 149000 | M84: Support & Maintenance | O84: Ashutosh Chauhan | Y84: 2025-10-08 | Z84: https://app.hubspot.com/contacts/243046792/record/0-3/180873330422
A85: 84 | B85: 156444963552 | D85: Absence Management Implementation | E85: City of Cincinnati | F85: Ohio | G85: Submitted | H85: No | J85: 45939 | K85: 45939 | M85: Platform Implementation (ERP, CRMs) | N85: Portal | O85: Ashutosh Chauhan | Y85: 2025-09-08 | Z85: https://app.hubspot.com/contacts/243046792/record/0-3/156444963552
A86: 85 | B86: 158110622443 | C86: RFP25-1003289 | D86: OFFICE 365 IMPLEMENTATION | E86: San Bernardino County Transportation Authority | F86: California | G86: Closed Lost | H86: Yes | I86: Interview | J86: 45964 | K86: 45939 | L86: 61000 | M86: Modernization / Migration | N86: Portal | O86: Ashutosh Chauhan | Q86: 2025-10-29 | Y86: 2025-09-09 | Z86: https://app.hubspot.com/contacts/243046792/record/0-3/158110622443
A87: 86 | B87: 157264848615 | C87: RFP #25-04 | D87: IT Managed Services | E87: City of Hudson Oaks | F87: Texas | G87: Closed Lost | H87: No | J87: 46042 | K87: 45939 | M87: Managed Services (MSP) | N87: Email | O87: Ashutosh Chauhan | Y87: 2025-09-08 | Z87: https://app.hubspot.com/contacts/243046792/record/0-3/157264848615
A88: 87 | B88: 168079320786 | C88: 5000003320 | D88: Cloud Developer | E88: California State Teachers' Retirement System | F88: California | G88: Submitted | H88: No | J88: 45939 | K88: 45940 | M88: Staff Augmentation | N88: Portal | O88: Abhishek Zalani | Y88: 2025-09-22 | Z88: https://app.hubspot.com/contacts/243046792/record/0-3/168079320786
A89: 88 | B89: 162088909561 | C89: 25-02CM | D89: Information Technology Services | E89: City of Palmer | F89: Alaska | G89: Submitted | H89: No | J89: 45940 | K89: 45940 | M89: Managed Services (MSP) | N89: Email | O89: Ashutosh Chauhan | Y89: 45915 | Z89: https://app.hubspot.com/contacts/243046792/record/0-3/162088909561
A90: 89 | B90: 163704495811 | D90: IT Infrastructure Assessment Study | E90: BLOOMINGTON PUBLIC TRANSPORTATION CORPORATION | F90: Indiana | G90: Closed Lost | H90: No | J90: 46030 | K90: 45940 | L90: 48300 | M90: Audits and Assessment | N90: Portal | O90: Ashutosh Chauhan | Y90: 2025-09-18 | Z90: https://app.hubspot.com/contacts/243046792/record/0-3/163704495811
A91: 90 | B91: 158191708877 | D91: INFORMATION TECHNOLOGY SOLUTIONS & SERVICES | E91: City of Benson | F91: Arizona | G91: Submitted | H91: No | J91: 45940 | K91: 45943 | L91: 192720 | M91: Managed Services (MSP) | N91: Portal | O91: Abhishek Zalani | Y91: 2025-09-10 | Z91: https://app.hubspot.com/contacts/243046792/record/0-3/158191708877
A92: 91 | B92: 167226060525 | C92: 26019 | D92: Student Engagement Application | E92: Fox Valley Technical College | F92: Wisconsin | G92: Submitted | H92: No | J92: 45943 | K92: 45943 | L92: 191800 | M92: Support & Maintenance;Platform Implementation (ERP, CRMs) | O92: Abhishek Zalani | Y92: 2025-09-22 | Z92: https://app.hubspot.com/contacts/243046792/record/0-3/167226060525
A93: 92 | B93: 182109882089 | D93: Enterprise Software Application Services Bench | E93: Los Angeles Unified School District (LAUSD) | F93: California | G93: Closed Lost | H93: No | J93: 46213 | K93: 45943 | M93: Staff Augmentation | N93: Portal | O93: Abhishek Zalani | Y93: 2025-10-09 | Z93: https://app.hubspot.com/contacts/243046792/record/0-3/182109882089 | AA93: No
A94: 93 | B94: 181172764371 | D94: INFORMATION TECHNOLOGY CONSULTANT SERVICES | E94: Township of Bloomfield | F94: New Jersey | G94: Submitted | H94: No | J94: 45946 | K94: 45943 | L94: 179860 | M94: Managed Services (MSP) | N94: Offline | O94: Jyothsna Nanda kishore | Y94: 2025-10-08 | Z94: https://app.hubspot.com/contacts/243046792/record/0-3/181172764371
A95: 94 | B95: 175110074066 | C95: 26-008 | D95: Business Analyst Consulting Services | E95: Northeast Wisconsin Technical College (NWTC) | F95: Wisconsin | G95: Closed Lost | H95: No | J95: 46162 | K95: 45943 | M95: Consulting | N95: Portal | O95: Jyothsna Nanda kishore | Y95: 2025-10-03 | Z95: https://app.hubspot.com/contacts/243046792/record/0-3/175110074066
A96: 95 | B96: 162089211630 | C96: 2025-122 | D96: Auto-Update Oracle System Integration Testing Environment | E96: Greater Cleveland Regional Transit Authority | F96: Ohio | G96: Interview | H96: Yes | I96: Interview | J96: 2026-03-05 | K96: 45943 | M96: Support & Maintenance | N96: Email | O96: Ashutosh Chauhan | P96: Interview Scheduled | Q96: 2025-11-14 | Y96: 2025-09-17 | Z96: https://app.hubspot.com/contacts/243046792/record/0-3/162089211630
A97: 96 | B97: 240974373562 | C97: Consolidated IT Services Bench | D97: LAUSD - Consolidated IT Services Bench | E97: Los Angeles Unified School District (LAUSD) | F97: California | G97: Closed Won | H97: Yes | I97: BAFO | J97: 46143 | K97: 45943 | M97: Staff Augmentation | N97: Portal | O97: Abhishek Zalani | P97: BAFO | R97: 2025-12-05 | S97: 2025-11-21 | U97: 46147 | Y97: 2025-10-09 | Z97: https://app.hubspot.com/contacts/243046792/record/0-3/240974373562 | AA97: No
A98: 97 | B98: 183834024660 | D98: Veeam Data Platform Advanced Universal Subscription (Rebid) | E98: City of Rancho Cucamonga | F98: California | G98: Closed Lost | H98: No | J98: 45957 | K98: 45944 | L98: 67000 | M98: Reseller | N98: Portal | O98: Ashutosh Chauhan | Y98: 2025-10-10 | Z98: https://app.hubspot.com/contacts/243046792/record/0-3/183834024660
A99: 98 | B99: 241471982294 | D99: Town of St. Michaels - Managed IT Services | E99: Town of St Michaels | F99: Maryland | G99: Closed Won | H99: No | J99: 45964 | K99: 45944 | L99: 74000 | M99: Managed Services (MSP) | N99: Email | O99: Abhishek Zalani | S99: 2025-10-22 | U99: 45981 | V99: In Process | Y99: 2025-10-01 | Z99: https://app.hubspot.com/contacts/243046792/record/0-3/241471982294 | AA99: Yes
A100: 99 | B100: 148302305009 | C100: 2025-012 | D100: TQ. Information Technology (IT) Services | E100: Brainerd Housing and Redevelopment Authority | F100: Minnesota | G100: Closed Lost | H100: No | J100: 45975 | K100: 45944 | L100: 25368 | M100: Managed Services (MSP) | N100: Offline | O100: Jyothsna Nanda kishore | Y100: 2025-08-29 | Z100: https://app.hubspot.com/contacts/243046792/record/0-3/148302305009
...

Sheet Awards
A1: S.No. | B1: HubSpot ID | C1: RFP Number | D1: Deal Name | E1: Agency | F1: Agency State | G1: Stage | H1: Interview Flag | I1: Interview Subcategory | J1: Bid Closing Date | K1: Submission Date | L1: Amount ($) | M1: Service Category | N1: Submission Mode | O1: Owner | P1: Interview Type | Q1: Interview Date | R1: BAFO Date | S1: Intent to Award Date | T1: Tentatively Awarded Date | U1: Awarded Date | V1: Award Status | W1: Won Reason | X1: Lost Reason | Y1: Created Date | Z1: HubSpot Link | AA1: Delivery Required
A2: 1 | B2: 126592758469 | C2: (RFQ) #T000599 | D2: New York Department of Financial Services - Data Governance Training | E2: New York Department of Financial Services | F2: New York | G2: Closed Won | H2: No | J2: 45526 | K2: 45527 | L2: 5800 | M2: Training | N2: Email | O2: Jyothsna Nanda kishore | S2: 2024-11-07 | U2: 45663 | V2: In Process | Y2: 2025-07-21 | Z2: https://app.hubspot.com/contacts/243046792/record/0-3/126592758469 | AA2: Yes
A3: 2 | B3: 127482765027 | C3: SW1025 | D3: Office of Management & Enterprise Services - IT Staffing | E3: Office of Management & Enterprise Services | F3: Oklahoma | G3: Closed Won | H3: No | J3: 45596 | K3: 45596 | M3: Staff Augmentation | N3: Portal | O3: Jyothsna Nanda kishore | Y3: 2025-07-23 | Z3: https://app.hubspot.com/contacts/243046792/record/0-3/127482765027 | AA3: No
A4: 3 | B4: 116521161421 | D4: NACCHO - CUSTOM JAVASCRIPT PROGRAMMING | E4: NACCHO | F4: D.C. | G4: Closed Won | H4: No | J4: 45614 | K4: 45614 | L4: 9225 | M4: Consulting | N4: Email | O4: Jyothsna Nanda kishore | S4: 2024-12-13 | U4: 45346 | Y4: 2025-07-09 | Z4: https://app.hubspot.com/contacts/243046792/record/0-3/116521161421 | AA4: Yes
A5: 4 | B5: 127482767062 | C5: 2024-013 | D5: Marin Housing Authority- Managed IT Services, CIO and Cybersecurity Services | E5: Marin Housing Authority | F5: California | G5: Closed Won | H5: No | J5: 45632 | K5: 45632 | L5: 838500 | M5: Managed Services (MSP) | N5: Portal | O5: Jyothsna Nanda kishore | S5: 2024-12-26 | U5: 45661 | Y5: 2025-07-23 | Z5: https://app.hubspot.com/contacts/243046792/record/0-3/127482767062 | AA5: Yes
A6: 5 | B6: 126590238401 | C6: RFQ #01-25 | D6: Macomb County - Microsoft 365 Migration | E6: Macomb County | F6: Michigan | G6: Closed Won | H6: Yes | I6: Interview | J6: 45701 | K6: 45670 | L6: 404900 | M6: Modernization / Migration | N6: Offline | O6: Jyothsna Nanda kishore | P6: Interview Scheduled | Q6: 2025-03-07 | S6: 2025-04-23 | U6: 45812 | V6: In Process | Y6: 2025-07-21 | Z6: https://app.hubspot.com/contacts/243046792/record/0-3/126590238401 | AA6: Yes
A7: 6 | B7: 127701416677 | C7: RFP- 282503 | D7: Arizona State University - Digital Accessibility Services | E7: Arizona State University | F7: Arizona | G7: Closed Won | H7: No | J7: 45679 | K7: 45679 | M7: Consulting;Training;Audits and Assessment | N7: Portal | O7: Jyothsna Nanda kishore | S7: 2025-07-16 | U7: 45912 | Y7: 2025-07-23 | Z7: https://app.hubspot.com/contacts/243046792/record/0-3/127701416677 | AA7: No
A8: 7 | B8: 127482766020 | D8: San Mateo County - Contingency Health IT Staffing | E8: County of San Mateo | F8: California | G8: Closed Won | H8: No | J8: 45719 | K8: 45716 | M8: Staff Augmentation | N8: Portal | O8: Arshdeep Kaur | S8: 2025-03-05 | U8: 45797 | Y8: 2025-07-23 | Z8: https://app.hubspot.com/contacts/243046792/record/0-3/127482766020 | AA8: No
A9: 8 | B9: 127685792505 | C9: EVT00010112 | D9: Kansas Dept. of Administration - Temporary Staffing Services | E9: Kansas Department of Administration | F9: Kansas | G9: Closed Won | H9: No | J9: 45737 | K9: 45737 | M9: Staff Augmentation | O9: Arshdeep Kaur | S9: 2025-04-23 | U9: 45772 | Y9: 2025-07-23 | Z9: https://app.hubspot.com/contacts/243046792/record/0-3/127685792505 | AA9: No
A10: 9 | B10: 127690112742 | D10: Illinois Department of Public Health- Data Literacy Training | E10: Illinois Department of Public Health | F10: Illinios | G10: Closed Won | H10: No | J10: 45743 | K10: 45743 | L10: 18499 | M10: Training | N10: Portal | O10: Jyothsna Nanda kishore | S10: 2025-05-05 | U10: 45868 | V10: In Process | Y10: 2025-07-23 | Z10: https://app.hubspot.com/contacts/243046792/record/0-3/127690112742 | AA10: Yes
A11: 10 | B11: 127482769082 | D11: Ohio Department of Natural Resources- H2O PROJECT MANAGEMENTTASK TACKING TOOLENHANCEMENTS-SALESFORCE DEVELOPER | E11: Ohio Department of Natural Resources | F11: Ohio | G11: Closed Won | H11: No | J11: 45747 | K11: 45747 | L11: 11275 | M11: Platform Implementation (ERP, CRMs) | N11: Portal | O11: Jyothsna Nanda kishore | S11: 2025-04-03 | U11: 45764 | V11: Completed | Y11: 2025-07-23 | Z11: https://app.hubspot.com/contacts/243046792/record/0-3/127482769082 | AA11: Yes
A12: 11 | B12: 114864632563 | C12: IT1638-25 | D12: Marion County - Oracle Support Services | E12: Marion County | F12: Oregon | G12: Closed Won | H12: No | J12: 45750 | K12: 45750 | L12: 100000 | M12: Support & Maintenance | N12: Portal | O12: Jyothsna Nanda kishore | S12: 2025-05-19 | U12: 45819 | V12: In Process | Y12: 2025-07-09 | Z12: https://app.hubspot.com/contacts/243046792/record/0-3/114864632563 | AA12: Yes
A13: 12 | B13: 127482750660 | D13: Metropolitan Water District of Southern California - ON-CALL INFORMATION TECHNOLOGY (IT) QUALITY ASSURANCE AND CONTROL, PROJECT MANAGEMENT, AND BUSINESS ANALYSIS SUPPORT SERVICES (RFQ-MN-1395) | E13: Metropolitan Water District of Southern California | F13: California | G13: Closed Won | H13: No | J13: 45755 | K13: 45755 | M13: Staff Augmentation | N13: Portal | O13: Madhav Mitruka | S13: 2025-07-22 | U13: 45860 | Y13: 2025-07-23 | Z13: https://app.hubspot.com/contacts/243046792/record/0-3/127482750660 | AA13: No
A14: 13 | B14: 126600317675 | C14: RFP S24262 | D14: SCVTA - Employee Application | E14: Santa Clara Valley Transportation Authority | F14: California | G14: Closed Won | H14: Yes | I14: Interview | J14: 45729 | K14: 45761 | L14: 140000 | M14: Custom development | N14: Portal | O14: Jyothsna Nanda kishore | P14: Interview Scheduled | Q14: 2025-05-08 | S14: 2025-06-26 | U14: 45902 | V14: In Process | Y14: 2025-07-21 | Z14: https://app.hubspot.com/contacts/243046792/record/0-3/126600317675 | AA14: Yes
A15: 14 | B15: 126595998395 | C15: DOR RFP 24/25-59 | D15: Florida Department of Revenue - SAP License Analysis | E15: Florida Department of Revenue | F15: Florida | G15: Closed Won | H15: No | J15: 45761 | K15: 45761 | L15: 58800 | M15: Audits and Assessment | N15: Offline | O15: Jyothsna Nanda kishore | S15: 2025-05-22 | U15: 45817 | V15: In Process | Y15: 2025-07-21 | Z15: https://app.hubspot.com/contacts/243046792/record/0-3/126595998395 | AA15: Yes
A16: 15 | B16: 235860602564 | C16: RFQ-AR-1398 | D16: Metropolitan Water District of Southern California - On-Call Information Technology Cybersecurity Services | E16: Metropolitan Water District of Southern California | F16: California | G16: Closed Won | H16: No | J16: 45999 | K16: 45771 | M16: Managed Services (MSP) | N16: Portal | O16: Madhav Mitruka | S16: 2025-12-02 | U16: 45993 | Y16: 2025-12-08 | Z16: https://app.hubspot.com/contacts/243046792/record/0-3/235860602564
A17: 16 | B17: 186570653428 | C17: 405 24R0019168C | D17: Texas Department of Public Safety - Cherwell Professional Services | E17: Texas Department of Public Safety | F17: Texas | G17: Closed Won | H17: No | J17: 45791 | K17: 45790 | L17: 148500 | M17: Managed Services (MSP) | N17: Email | O17: Ashley Lamaniya | S17: 2025-10-09 | U17: 45947 | Y17: 2025-10-13 | Z17: https://app.hubspot.com/contacts/243046792/record/0-3/186570653428 | AA17: Yes
A18: 17 | B18: 127482765035 | C18: RFP NO. NC- 2025-14 | D18: Fresno County Superintendent of Schools - Computer Maintenance & Technology Support Services | E18: FRESNO COUNTY SUPERINTENDENT OF SCHOOLS | F18: California | G18: Closed Won | H18: No | J18: 45796 | K18: 45796 | L18: 500000 | M18: Consulting;Support & Maintenance | N18: Email | O18: Arshdeep Kaur | S18: 2025-06-13 | U18: 45968 | V18: In Process | Y18: 2025-07-23 | Z18: https://app.hubspot.com/contacts/243046792/record/0-3/127482765035 | AA18: No
A19: 18 | B19: 108072562388 | D19: Madison Metropolitan Sewerage District - IT Augmentation Partner (SOW 1) | E19: Madison Metropolitan Sewerage District | F19: Wisconsin | G19: Closed Won | H19: Yes | I19: Interview | J19: 45903 | K19: 45801 | L19: 1081349.5 | M19: Managed Services (MSP) | O19: Madhav Mitruka | P19: Interview Scheduled | Q19: 2025-07-28 | S19: 2025-08-14 | U19: 45918 | V19: In Process | Y19: 2025-06-25 | Z19: https://app.hubspot.com/contacts/243046792/record/0-3/108072562388 | AA19: Yes
A20: 19 | B20: 127743477490 | D20: EPIC 6- RFP 21.25 Technology Solutions & Services | E20: Region 6 Education Service Center | F20: Texas | G20: Closed Won | H20: No | J20: 46142 | K20: 45807 | M20: Staff Augmentation | N20: Portal | O20: Jyothsna Nanda kishore | S20: 2025-06-16 | U20: 45831 | Y20: 2025-07-23 | Z20: https://app.hubspot.com/contacts/243046792/record/0-3/127743477490 | AA20: No
A21: 20 | B21: 135608301264 | C21: RFP-3578 | D21: Port Houston - Managed Network Operations Center Services | E21: Port Houston | F21: Texas | G21: Closed Won | H21: Yes | I21: Interview | J21: 45917 | K21: 45819 | L21: 1183000 | M21: Managed Services (MSP) | O21: Madhav Mitruka | P21: Interview Scheduled | Q21: 2025-07-23 | S21: 2025-09-23 | U21: 45967 | V21: In Process | Y21: 2025-08-01 | Z21: https://app.hubspot.com/contacts/243046792/record/0-3/135608301264 | AA21: Yes
A22: 21 | B22: 175110048474 | D22: Commonwealth of Pennsylvania - Agile ITQ Development | E22: Commonwealth of Pennsylvania | F22: Pennsylvania | G22: Closed Won | H22: No | J22: 45932 | K22: 45832 | M22: Staff Augmentation | N22: Portal | O22: Madhav Mitruka | S22: 2025-10-02 | U22: 45932 | Y22: 2025-10-02 | Z22: https://app.hubspot.com/contacts/243046792/record/0-3/175110048474 | AA22: No
A23: 22 | B23: 181172764367 | D23: Monroe County - Temporary Personnel Services for Information Technology | E23: Monroe County | F23: New York | G23: Closed Won | H23: No | J23: 45835 | K23: 45833 | M23: Platform Implementation (ERP, CRMs);Support & Maintenance | N23: Email | O23: Jyothsna Nanda kishore | S23: 2025-10-08 | U23: 45938 | Y23: 2025-10-08 | Z23: https://app.hubspot.com/contacts/243046792/record/0-3/181172764367 | AA23: Yes
A24: 23 | B24: 127677476588 | C24: 23-030 | D24: San Antonio Independent School District - Miscellaneous Consultant Services | E24: San Antonio Independent School District | F24: Texas | G24: Closed Won | H24: No | J24: 45838 | K24: 45838 | M24: Staff Augmentation | N24: Portal | O24: Jyothsna Nanda kishore | S24: 2025-07-11 | U24: 45849 | V24: In Process | Y24: 2025-07-23 | Z24: https://app.hubspot.com/contacts/243046792/record/0-3/127677476588 | AA24: No
A25: 24 | B25: 110712028891 | D25: Oregon League of Cities - STAFFING SERVICES WITH RELATED SERVICES AND SOLUTIONS | E25: Oregon League of Cities | F25: Oregon | G25: Closed Won | H25: No | J25: 46007 | K25: 45859 | M25: Staff Augmentation | N25: Portal | O25: Madhav Mitruka | S25: 2025-12-15 | U25: 46066 | Y25: 2025-07-01 | Z25: https://app.hubspot.com/contacts/243046792/record/0-3/110712028891 | AA25: Yes
A26: 25 | B26: 127424133880 | C26: 5400028271 | D26: State of South Carolina - STC Dynamics Managed Service Provider | E26: State of South Carolina | F26: South Carolina | G26: Closed Won | H26: No | J26: 45971 | K26: 45860 | M26: Managed Services (MSP);Staff Augmentation | N26: Email | O26: Jyothsna Nanda kishore | S26: 2025-11-06 | U26: 45967 | Y26: 2025-07-22 | Z26: https://app.hubspot.com/contacts/243046792/record/0-3/127424133880 | AA26: Yes
A27: 26 | B27: 114864544502 | D27: University System of New Hampshire - Workday Related Staff Augmentation and Project Work | E27: University System of New Hampshire | F27: New Hampshire | G27: Closed Won | H27: No | J27: 45981 | K27: 45861 | M27: Staff Augmentation | N27: Portal | O27: Madhav Mitruka | S27: 2025-11-20 | U27: 46009 | Y27: 2025-07-08 | Z27: https://app.hubspot.com/contacts/243046792/record/0-3/114864544502
A28: 27 | B28: 134329484998 | D28: Collier County - OPENCollier MPO WordPress Website Maintenance & Hosting | E28: Collier County | F28: Florida | G28: Closed Won | H28: No | J28: 45924 | K28: 45867 | L28: 3990 | M28: Support & Maintenance | N28: Portal | O28: Madhav Mitruka | S28: 2025-09-24 | U28: 45924 | Y28: 2025-07-29 | Z28: https://app.hubspot.com/contacts/243046792/record/0-3/134329484998
A29: 29 | B29: 120592685811 | C29: RFQ-1001295 | D29: Iowa State University - Cybersecurity Services for Iowa Political Subdivisions | E29: Iowa State University | F29: Iowa | G29: Closed Won | H29: No | J29: 45981 | K29: 45877 | M29: Audits and Assessment | N29: Portal | O29: Jyothsna Nanda kishore | S29: 2025-11-20 | U29: 46156 | Y29: 2025-07-15 | Z29: https://app.hubspot.com/contacts/243046792/record/0-3/120592685811 | AA29: Yes
A30: 32 | B30: 126587718330 | D30: Alachua County Library District - E-Rate Cybersecurity Pilot Program - Next Generation Firewall | E30: Alachua County Library District | F30: Florida | G30: Closed Won | H30: No | J30: 45905 | K30: 45890 | L30: 73000 | M30: Consulting | N30: Portal | O30: Yashaswini Gautam | S30: 2025-09-05 | U30: 46132 | Y30: 2025-07-21 | Z30: https://app.hubspot.com/contacts/243046792/record/0-3/126587718330
A31: 33 | B31: 144659629780 | C31: 02805095 | D31: St. Johns County - Veeam VBR Enterprise Basic Maintenance License Renew | E31: St. Johns County | F31: Florida | G31: Closed Won | H31: No | J31: 45910 | K31: 45891 | L31: 15712 | M31: Reseller | N31: Email | O31: Madhav Mitruka | S31: 2025-09-22 | U31: 45922 | Y31: 2025-08-22 | Z31: https://app.hubspot.com/contacts/243046792/record/0-3/144659629780
A32: 34 | B32: 137815198453 | C32: RFP No. FIN0825-001 | D32: Municipal Water District of Orange County (MWDOC) Enterprise Planning Resource (ERP) System Architecture and Configuration (RFP No. FIN0825-001) | E32: Municipal Water District of Orange County (MWDOC) | F32: California | G32: Closed Won | H32: Yes | I32: Interview | J32: 45936 | K32: 45905 | L32: 90000 | M32: Platform Implementation (ERP, CRMs) | N32: Email | O32: Madhav Mitruka | P32: Interview Scheduled | Q32: 2025-09-17 | S32: 2025-10-13 | U32: 45972 | V32: In Process | Y32: 2025-08-06 | Z32: https://app.hubspot.com/contacts/243046792/record/0-3/137815198453 | AA32: Yes
A33: 35 | B33: 145845264086 | D33: City of Olmos Park - Information Technology Services | E33: City of Olmos Park | F33: Texas | G33: Closed Won | H33: No | J33: 45918 | K33: 45911 | L33: 184400 | M33: Managed Services (MSP) | N33: Offline | O33: Arshdeep Kaur | S33: 2025-09-18 | U33: 45946 | V33: In Process | Y33: 2025-08-26 | Z33: https://app.hubspot.com/contacts/243046792/record/0-3/145845264086 | AA33: Yes
A34: 36 | B34: 134489494217 | D34: Florida Department of Management Services - Prequalification for Information Technology Staff Augmentation Services (Supplemental) 2025 | E34: Florida Department of Management Services | F34: Florida | G34: Closed Won | H34: No | J34: 45932 | K34: 45916 | M34: Staff Augmentation | N34: Portal | O34: Madhav Mitruka | S34: 2025-09-16 | U34: 46049 | Y34: 2025-07-30 | Z34: https://app.hubspot.com/contacts/243046792/record/0-3/134489494217 | AA34: No
A35: 37 | B35: 144653136611 | D35: Western Municipal Water District - Data Solution Design, Build & Implementation, Western Municipal Water District (Western Water) | E35: Western Municipal Water District | F35: California | G35: Closed Won | H35: No | J35: 46009 | K35: 45918 | L35: 143460 | M35: Modernization / Migration | N35: Portal | O35: Jyothsna Nanda kishore | S35: 2025-11-18 | U35: 45973 | V35: In Process | Y35: 2025-08-22 | Z35: https://app.hubspot.com/contacts/243046792/record/0-3/144653136611 | AA35: Yes
A36: 38 | B36: 159541459657 | C36: WSD001 | D36: County of Los Angeles Department of Public Works - Microsoft Power Platform Training | E36: County of Los Angeles Department of Public Works | F36: California | G36: Closed Won | H36: No | J36: 46114 | K36: 45925 | L36: 12000 | M36: Training | N36: Email | O36: Jyothsna Nanda kishore | S36: 2026-04-02 | U36: 46113 | Y36: 2025-09-12 | Z36: https://app.hubspot.com/contacts/243046792/record/0-3/159541459657 | AA36: Yes
A37: 39 | B37: 158113558258 | D37: TRIMET - Data Center Assessment and Risk Mitigation Strategy | E37: Tri-County Metropolitan Transportation District of Oregon | F37: Oregon | G37: Closed Won | H37: Yes | I37: BAFO | J37: 46143 | K37: 45929 | L37: 20893 | M37: Audits and Assessment | N37: Portal | O37: Ashutosh Chauhan | P37: BAFO | R37: 2025-10-15 | S37: 2025-10-20 | U37: 45953 | Y37: 2025-09-10 | Z37: https://app.hubspot.com/contacts/243046792/record/0-3/158113558258 | AA37: Yes
A38: 40 | B38: 126595998432 | C38: RFP-554-2025-0052-0-2025/AH | D38: Raleigh Durham Airport Authority (NC) - SharePoint Consultant | E38: Raleigh Durham Airport Authority [NC] | F38: North Carolina | G38: Intent to Award | H38: No | J38: 46052 | K38: 45932 | L38: 18830 | M38: Consulting | N38: Portal | O38: Madhav Mitruka | S38: 46052 | Y38: 2025-07-21 | Z38: https://app.hubspot.com/contacts/243046792/record/0-3/126595998432
A39: 41 | B39: 161660341982 | D39: Greene County - PROFESSIONAL CONSULTANT SERVICES | E39: Greene County | F39: New York | G39: Closed Won | H39: No | J39: 46143 | K39: 45932 | M39: Staff Augmentation | N39: Offline | O39: Arshdeep Kaur | S39: 2025-12-09 | U39: 46093 | Y39: 2025-09-17 | Z39: https://app.hubspot.com/contacts/243046792/record/0-3/161660341982 | AA39: No
A40: 42 | B40: 158113559231 | D40: City of San Carlos - Legacy File Server Migration to SharePoint Modernization | E40: City of San Carlos | F40: California | G40: Closed Won | H40: Yes | I40: Interview | J40: 46149 | K40: 45936 | L40: 98000 | M40: Modernization / Migration | N40: Email | O40: Abhishek Zalani | P40: Interview Scheduled | Q40: 2025-12-10 | S40: 2026-01-01 | U40: 46031 | Y40: 2025-09-10 | Z40: https://app.hubspot.com/contacts/243046792/record/0-3/158113559231
A41: 44 | B41: 240974373562 | C41: Consolidated IT Services Bench | D41: LAUSD - Consolidated IT Services Bench | E41: Los Angeles Unified School District (LAUSD) | F41: California | G41: Closed Won | H41: Yes | I41: BAFO | J41: 46143 | K41: 45943 | M41: Staff Augmentation | N41: Portal | O41: Abhishek Zalani | P41: BAFO | R41: 2025-12-05 | S41: 2025-11-21 | U41: 46147 | Y41: 2025-10-09 | Z41: https://app.hubspot.com/contacts/243046792/record/0-3/240974373562 | AA41: No
A42: 45 | B42: 241471982294 | D42: Town of St. Michaels - Managed IT Services | E42: Town of St Michaels | F42: Maryland | G42: Closed Won | H42: No | J42: 45964 | K42: 45944 | L42: 74000 | M42: Managed Services (MSP) | N42: Email | O42: Abhishek Zalani | S42: 2025-10-22 | U42: 45981 | V42: In Process | Y42: 2025-10-01 | Z42: https://app.hubspot.com/contacts/243046792/record/0-3/241471982294 | AA42: Yes
A43: 46 | B43: 159501546182 | C43: 25-082 | D43: [Shared Award] El Paso County - Amazon Web Services Website Managed ServicesID: 25-082 | E43: El Paso County | F43: Colorado | G43: Closed Won | H43: Yes | I43: Interview | J43: 46111 | K43: 45945 | L43: 148500 | M43: Managed Services (MSP) | N43: Portal | O43: Jyothsna Nanda kishore | Q43: 2025-12-17 | S43: 2026-02-03 | U43: 46068 | V43: In Process | Y43: 2025-09-12 | Z43: https://app.hubspot.com/contacts/243046792/record/0-3/159501546182 | AA43: Yes
A44: 47 | B44: 169109642951 | C44: 242-25-00022 | D44: Christopher Newport University - Consulting & Training Support - Workday Adaptive Planning | E44: Christopher Newport University | F44: Virginia | G44: Closed Won | H44: Yes | I44: BAFO | J44: 46049 | K44: 45948 | L44: 25127 | M44: Consulting;Training | N44: Offline | O44: Ashutosh Chauhan | P44: Interview Scheduled | Q44: 2025-12-08 | R44: 2025-12-19 | S44: 2026-01-14 | U44: 46048 | V44: Awarded | Y44: 2025-09-24 | Z44: https://app.hubspot.com/contacts/243046792/record/0-3/169109642951 | AA44: Yes
A45: 48 | B45: 145845271269 | C45: PI25-0148F | D45: City of Tacoma - Computerized Maintenance Management System | E45: City of Tacoma | F45: Washington | G45: Intent to Award | H45: No | J45: 45958 | K45: 45958 | L45: 83098 | M45: Platform Implementation (ERP, CRMs) | N45: Email | O45: Abhishek Zalani | S45: 45966 | Y45: 2025-08-26 | Z45: https://app.hubspot.com/contacts/243046792/record/0-3/145845271269 | AA45: Yes
A46: 49 | B46: 200821843683 | D46: Cuyahoga County Board of Elections - Veeam Data Platform Renewal | E46: Cuyahoga County Board of Elections | F46: Ohio | G46: Closed Won | H46: No | J46: 45980 | K46: 45959 | L46: 6078.19 | M46: Reseller | N46: Portal | O46: Ashutosh Chauhan | S46: 2025-11-18 | U46: 45979 | Y46: 2025-10-27 | Z46: https://app.hubspot.com/contacts/243046792/record/0-3/200821843683 | AA46: No
A47: 50 | B47: 182109882068 | D47: Greene County - Professional Consultant Services (Rebid) | E47: Greene County | F47: New York | G47: Closed Won | H47: No | J47: 46097 | K47: 45968 | M47: Staff Augmentation | N47: Offline | O47: Abhishek Zalani | S47: 2025-12-09 | U47: 46079 | Y47: 2025-10-09 | Z47: https://app.hubspot.com/contacts/243046792/record/0-3/182109882068 | AA47: No
A48: 51 | B48: 209641964265 | D48: City of Sunnyvale - Professional and Technical IT Contracting Services for SharePoint Migration | E48: City of Sunnyvale | F48: California | G48: Closed Won | H48: Yes | I48: Interview | J48: 46058 | K48: 45979 | L48: 68400 | M48: Modernization / Migration | O48: Jyothsna Nanda kishore | Q48: 2025-12-11 | S48: 2025-12-30 | U48: 46022 | Y48: 2025-11-03 | Z48: https://app.hubspot.com/contacts/243046792/record/0-3/209641964265 | AA48: Yes
A49: 53 | B49: 202061536982 | D49: New Mexico Finance Authority (NMFA) - INFORMATION TECHNOLOGY (IT) MANAGED SERVICE PROVIDER AND NETWORK OPERATIONS CENTER (NOC) | E49: New Mexico Finance Authority (“NMFA”) | F49: New Mexico | G49: Closed Won | H49: Yes | I49: BAFO | J49: 46142 | K49: 45996 | L49: 351426 | M49: Managed Services (MSP) | N49: Email | O49: Ashutosh Chauhan | P49: Interview Scheduled | Q49: 2026-02-13 | R49: 2026-01-20 | S49: 2026-02-19 | U49: 46141 | Y49: 2025-10-28 | Z49: https://app.hubspot.com/contacts/243046792/record/0-3/202061536982 | AA49: Yes
A50: 54 | B50: 231581420260 | D50: New Castle County - Information Technology Services | E50: New Castle County | F50: Delaware | G50: Closed Won | H50: No | J50: 46083 | K50: 45999 | M50: Staff Augmentation | N50: Offline | O50: Jyothsna Nanda kishore | S50: 2026-02-13 | U50: 46066 | Y50: 2025-12-02 | Z50: https://app.hubspot.com/contacts/243046792/record/0-3/231581420260 | AA50: No
A51: 56 | B51: 212696339180 | C51: AI02-26 | D51: Houston-Galveston Area Council - AI Consulting Services | E51: Houston-Galveston Area Council | F51: Texas | G51: Closed Won | H51: No | J51: 46154 | K51: 46009 | M51: Consulting;Staff Augmentation | N51: Portal | O51: Ashutosh Chauhan | S51: 2026-04-30 | U51: 46119 | Y51: 2025-11-10 | Z51: https://app.hubspot.com/contacts/243046792/record/0-3/212696339180 | AA51: No
A52: 57 | B52: 235886616288 | D52: LEAD CHARTER SCHOOL - Rebid- Information Technology Services | E52: LEAD CHARTER SCHOOL | F52: New Jersey | G52: Intent to Award | H52: No | J52: 46072 | K52: 46023 | L52: 24750 | M52: Managed Services (MSP) | N52: Offline | O52: Jyothsna Nanda kishore | S52: 46062 | U52: 46062 | Y52: 2025-12-09 | Z52: https://app.hubspot.com/contacts/243046792/record/0-3/235886616288 | AA52: Yes
A53: 58 | B53: 235964612297 | D53: North Central Texas Council of Governments - AI Governance, Compliance, and Enablement Platform | E53: North Central Texas Council of Governments | F53: TEXAS | G53: Closed Won | H53: No | J53: 46141 | K53: 46038 | M53: Consulting | N53: Portal | O53: Ashutosh Chauhan | S53: 2026-03-10 | U53: 46148 | V53: Awarded | Y53: 2025-12-09 | Z53: https://app.hubspot.com/contacts/243046792/record/0-3/235964612297 | AA53: No
A54: 59 | B54: 225906287352 | D54: Insurance Reserve Fund - Small Software Application Development | E54: Insurance Reserve Fund | F54: South Carolina | G54: Intent to Award | H54: No | J54: 46048 | K54: 46048 | M54: Staff Augmentation | N54: Portal | O54: Ashutosh Chauhan | S54: 46099 | U54: 46099 | Y54: 2025-11-24 | Z54: https://app.hubspot.com/contacts/243046792/record/0-3/225906287352
A55: 60 | B55: 275926212329 | D55: Village of Tinley Park - MICROSOFT OFFICE 365 LICESING | E55: Village of Tinley Park | F55: Illinois | G55: Closed Won | H55: No | J55: 46113 | K55: 46059 | L55: 114400 | M55: Reseller | N55: Offline | O55: Jyothsna Nanda kishore | S55: 2026-02-09 | U55: 46062 | Y55: 2026-01-28 | Z55: https://app.hubspot.com/contacts/243046792/record/0-3/275926212329 | AA55: No
A56: 61 | B56: 267386743501 | D56: University of South Carolina - FPB – Direct Placement Staffing Services for IT Positions | E56: University of South Carolina | F56: South Carolina | G56: Closed Won | H56: No | J56: 46120 | K56: 46059 | M56: Staff Augmentation | N56: Portal | O56: Jyothsna Nanda kishore | S56: 2026-02-26 | U56: 46079 | Y56: 2026-01-20 | Z56: https://app.hubspot.com/contacts/243046792/record/0-3/267386743501 | AA56: No
A57: 62 | B57: 277951244006 | D57: City of Kenai - IT Disaster Response Plan | E57: City of Kenai | F57: Alaska | G57: Closed Won | H57: No | J57: 46097 | K57: 46065 | L57: 16800 | M57: Consulting | N57: Offline | O57: Abhishek Zalani | S57: 2026-02-24 | U57: 46100 | V57: Awarded | Y57: 2026-01-29 | Z57: https://app.hubspot.com/contacts/243046792/record/0-3/277951244006 | AA57: Yes
A58: 63 | B58: 285814477558 | D58: City of Long Beach - RFQ - 1400 Long Beach Cybersecurity Grant Program | E58: City of Long Beach | F58: California | G58: Closed Won | H58: No | J58: 46113 | K58: 46079 | L58: 123785 | M58: Audits and Assessment | N58: Portal | O58: Jyothsna Nanda kishore | S58: 2026-03-12 | U58: 46084 | Y58: 2026-02-04 | Z58: https://app.hubspot.com/contacts/243046792/record/0-3/285814477558 | AA58: Yes
A59: 64 | B59: 290824554187 | D59: Navajo Housing Authority - Cybersecurity Policy and Protocol Consultant Services | E59: Navajo Housing Authority | F59: Arizona | G59: Closed Won | H59: No | J59: 46097 | K59: 46080 | L59: 7825 | M59: Consulting | N59: Email | O59: Savya Atrey | S59: 2026-03-30 | U59: 46097 | V59: Awarded | Y59: 2026-02-09 | Z59: https://app.hubspot.com/contacts/243046792/record/0-3/290824554187 | AA59: Yes
A60: 65 | B60: 305108054745 | D60: City of Stamford - Technology Data Architect Services | E60: City of Stamford | F60: Connecticut | G60: Closed Won | H60: Yes | I60: Interview | J60: 46135 | K60: 46093 | L60: 47775 | M60: Consulting;Staff Augmentation | N60: Portal | O60: Savya Atrey | P60: Interview Scheduled | Q60: 2026-04-20 | S60: 2026-04-22 | U60: 46142 | Y60: 2026-02-24 | Z60: https://app.hubspot.com/contacts/243046792/record/0-3/305108054745 | AA60: Yes
A61: 66 | B61: 323517591239 | D61: Community Action Partnership of Kern - CAPK SOW 1 + AI Training | E61: Community Action Partnership of Kern | F61: California | G61: Closed Won | H61: No | J61: 46296 | K61: 46115 | L61: 35756.1 | M61: Consulting;Managed Services (MSP) | O61: Ashutosh Chauhan | S61: 46156 | U61: 46156 | Y61: 2026-05-04 | Z61: https://app.hubspot.com/contacts/243046792/record/0-3/323517591239
A62: 67 | B62: 323528390341 | D62: New Mexico Finance Authority (NMFA) - IT MSP & NOC NMFA Additional SOW | E62: New Mexico Finance Authority (“NMFA”) | F62: New Mexico | G62: Closed Won | H62: No | J62: 46184 | K62: 46134 | L62: 67440 | M62: Managed Services (MSP) | O62: Ashutosh Chauhan | S62: 2026-05-04 | U62: 2026-06-09 | Y62: 2026-05-04 | Z62: https://app.hubspot.com/contacts/243046792/record/0-3/323528390341
A63: 68 | B63: 320213008064 | D63: Alaska Department of Administration - ONLINE WEB-BASED TRAINING | E63: Alaska Department of Administration | F63: Alaska | G63: Closed Won | H63: No | J63: 46191 | K63: 46139 | L63: 37800 | M63: Training | O63: Jyothsna Nanda kishore | S63: 2026-04-30 | U63: 2026-04-30 | Y63: 2026-04-09 | Z63: https://app.hubspot.com/contacts/243046792/record/0-3/320213008064 | AA63: Yes
A64: 69 | B64: 325724065471 | D64: Kodiak Island Borough - Test Environment Configuration Services | E64: Kodiak Island Borough | F64: Alaska | G64: Closed Won | H64: No | J64: 46231 | K64: 46168 | L64: 14280 | M64: Modernization / Migration | N64: Email | O64: Ashutosh Chauhan | S64: 46181 | U64: 46227 | Y64: 46161 | Z64: https://app.hubspot.com/contacts/243046792/record/0-3/325724065471
A65: 70 | B65: 116977709757 | C65: RCA-017-25010066 | D65: Orange County - ON-LINE MARKETPLACE FOR CLOUD SERVICES AND SOFTWARE | E65: Orange County | F65: California | G65: Closed Won | H65: No | J65: 45575 | K65: 45575 | L65: 0 | M65: Consulting;Reseller | O65: Ashutosh Chauhan | S65: 2025-01-09 | U65: 45688 | Y65: 2025-07-10 | Z65: https://app.hubspot.com/contacts/243046792/record/0-3/116977709757 | AA65: No
A66: 71 | B66: 116977709771 | C66: RFP-25-0005 | D66: NEIGHBORWORKS AMERICA - IT SERVICES (SOW) | E66: NeighborWorks America | F66: Washington, D.C. | G66: Closed Won | H66: No | J66: 45631 | K66: 45631 | M66: Staff Augmentation | O66: Amber Soni | S66: 2025-04-09 | U66: 45840 | Y66: 2025-07-10 | Z66: https://app.hubspot.com/contacts/243046792/record/0-3/116977709771 | AA66: No
A67: 72 | B67: 116977709756 | D67: Hazelwood School District - Hazelwood Information Technology Audit Services | E67: Hazelwood School District | F67: Missouri | G67: Closed Won | H67: No | J67: 45713 | K67: 45713 | L67: 48500 | M67: Audits and Assessment | O67: Yashaswini Gautam | S67: 2025-04-28 | U67: 45783 | V67: In Process | Y67: 2025-07-10 | Z67: https://app.hubspot.com/contacts/243046792/record/0-3/116977709756 | AA67: Yes
A68: 73 | B68: 269389012723 | C68: COVB-25-101486 | D68: City of Virginia Beach - IT Services | E68: City of Virginia Beach | F68: Virginia | G68: Closed Won | H68: No | J68: 45713 | K68: 45713 | L68: 0 | M68: Staff Augmentation | O68: Ashutosh Chauhan | S68: 2026-01-13 | U68: 46147 | Y68: 2026-01-20 | Z68: https://app.hubspot.com/contacts/243046792/record/0-3/269389012723 | AA68: No
A69: 75 | B69: 127590445803 | D69: Roswell Park Comprehensive Cancer Centre - IT Staffing and Professional Services | E69: Roswell Park Comprehensive Cancer Centre | F69: New York | G69: Closed Won | H69: No | J69: 45469 | K69: 45485 | M69: Consulting;Staff Augmentation | O69: Madhav Mitruka | S69: 2025-01-09 | U69: 45706 | Y69: 2025-07-23 | Z69: https://app.hubspot.com/contacts/243046792/record/0-3/127590445803 | AA69: No
A70: 76 | B70: 123670192881 | C70: 24-31 | D70: Arapahoe County - IT RECRUITMENT AND STAFFING | E70: Arapahoe County | F70: Colorado | G70: Closed Won | H70: No | J70: 45609 | M70: Staff Augmentation | O70: Jyothsna Nanda kishore | S70: 2025-01-29 | U70: 45775 | Y70: 2025-07-18 | Z70: https://app.hubspot.com/contacts/243046792/record/0-3/123670192881 | AA70: No
A71: 77 | B71: 114864632551 | C71: F25-077 | D71: City of Sunnyvale - Group 4, Software/Application/Database Development, Business Requirements Analysis, and Integration Services | E71: City of Sunnyvale | F71: California | G71: Closed Won | H71: No | J71: 45610 | M71: Staff Augmentation | N71: Email | O71: Jyothsna Nanda kishore | S71: 2025-02-18 | U71: 45706 | Y71: 2025-07-09 | Z71: https://app.hubspot.com/contacts/243046792/record/0-3/114864632551 | AA71: No
A72: 78 | B72: 127678196421 | C72: RFQ 24 - 00332 | D72: HRT - Workday HCM Staffing Services | E72: Hampton Roads Transit | F72: Virginia | G72: Closed Won | H72: Yes | I72: Interview | J72: 45685 | L72: 10000 | M72: Staff Augmentation | O72: Arshdeep Kaur | P72: Interview Scheduled | Q72: 2025-02-07 | S72: 2025-02-25 | U72: 45715 | V72: In Process | Y72: 2025-07-23 | Z72: https://app.hubspot.com/contacts/243046792/record/0-3/127678196421 | AA72: Yes
A73: 79 | B73: 127590445777 | D73: State of South Dakota Department of Social Services - Temporary Professional Staff Services 2 | E73: State of South Dakota Department of Social Services | F73: South Dakota | G73: Closed Won | H73: No | J73: 45729 | K73: 45729 | M73: Staff Augmentation | O73: Madhav Mitruka | S73: 2025-04-21 | U73: 45846 | Y73: 2025-07-23 | Z73: https://app.hubspot.com/contacts/243046792/record/0-3/127590445777 | AA73: No
A74: 80 | B74: 142851074788 | C74: RFQ-DH-1394 | D74: Metropolitan Water District of Southern California - ON-CALL INFORMATION TECHNOLOGY INFRASTRUCTURE SERVICES | E74: Metropolitan Water District of Southern California | F74: California | G74: Closed Won | H74: No | J74: 45743 | M74: Staff Augmentation | N74: Portal | O74: Jyothsna Nanda kishore | S74: 2025-07-25 | U74: 45863 | Y74: 2025-08-19 | Z74: https://app.hubspot.com/contacts/243046792/record/0-3/142851074788 | AA74: No
A75: 81 | B75: 132776626904 | D75: Metropolitan Water District of Southern California - ON-CALL INFORMATION TECHNOLOGY (IT) APPLICATION SUPPORT SERVICES (RFQ-DS-1397) | E75: Metropolitan Water District of Southern California | F75: California | G75: Closed Won | H75: No | J75: 45757 | M75: Staff Augmentation | O75: Madhav Mitruka | S75: 2025-07-28 | U75: 45866 | Y75: 2025-07-29 | Z75: https://app.hubspot.com/contacts/243046792/record/0-3/132776626904 | AA75: No
A76: 82 | B76: 127678196440 | D76: MINNESOTA JUDICIAL BRANCH - IT Technical/infrastructure Services, Information Technology Application Development And Support Services & Data Science And Machine Learning Services | E76: Minnesota Judicial Branch | F76: Minnesota | G76: Closed Won | H76: No | J76: 45776 | M76: Staff Augmentation | O76: Arshdeep Kaur | S76: 2025-07-08 | U76: 45896 | Y76: 2025-07-23 | Z76: https://app.hubspot.com/contacts/243046792/record/0-3/127678196440 | AA76: No
A77: 83 | B77: 127590445789 | D77: State of Vermont (Department of Buildings and General Services) - Retainer Contract Opportunity for Information Technology (IT) Services | E77: State of Vermont (Department of Buildings and General Services) | F77: Vermont | G77: Closed Won | H77: No | J77: 45807 | K77: 45806 | M77: Staff Augmentation | O77: Madhav Mitruka | S77: 2025-06-28 | U77: 46043 | Y77: 2025-07-23 | Z77: https://app.hubspot.com/contacts/243046792/record/0-3/127590445789 | AA77: No
A78: 84 | B78: 135198825206 | C78: 24-25-78 | D78: City of Santa Clara - IT Project Management & Consulting Services | E78: City of Santa Clara | F78: California | G78: Closed Won | H78: Yes | I78: Interview | J78: 45880 | M78: Consulting | O78: Madhav Mitruka | P78: Interview Scheduled | Q78: 2025-07-23 | S78: 2025-08-01 | U78: 45971 | Y78: 2025-08-01 | Z78: https://app.hubspot.com/contacts/243046792/record/0-3/135198825206 | AA78: No
A79: 85 | B79: 168988159693 | C79: 6000002323 | D79: Port Authority of New York New Jersey - Performance of Expert Professional Airport Data Analysis and Business Intelligence Consulting Services during 2025 through 2029 | E79: Port Authority of New York New Jersey | F79: New York | G79: Closed Won | H79: No | J79: 45924 | K79: 45580 | L79: 0 | M79: Staff Augmentation | O79: Yashaswini Gautam | S79: 2025-09-23 | U79: 45938 | Y79: 2025-09-24 | Z79: https://app.hubspot.com/contacts/243046792/record/0-3/168988159693
A80: 86 | B80: 169111068380 | C80: 6000002328 | D80: Port Authority of New York New Jersey - Performance of Expert Professional Airport Information Technology and Innovation Consulting Services | E80: Port Authority of New York New Jersey | F80: New York | G80: Closed Won | H80: No | J80: 45924 | K80: 45580 | L80: 0 | M80: Staff Augmentation | O80: Yashaswini Gautam | S80: 2025-09-23 | U80: 45938 | Y80: 2025-09-24 | Z80: https://app.hubspot.com/contacts/243046792/record/0-3/169111068380 | AA80: No
A81: 87 | B81: 169108930291 | C81: RFQ-AR-1399 | D81: Metropolitan Water District of Southern California - ON-CALL INFORMATION TECHNOLOGY SOFTWARE ASSET MANAGEMENT SERVICES | E81: Metropolitan Water District of Southern California | F81: California | G81: Closed Won | H81: No | J81: 45924 | M81: Consulting | O81: Madhav Mitruka | S81: 2025-09-24 | U81: 45924 | Y81: 2025-09-24 | Z81: https://app.hubspot.com/contacts/243046792/record/0-3/169108930291 | AA81: Yes
A82: 88 | B82: 140123456196 | C82: 24-RFP-10 | D82: Metropolitan Water Reclamation District of Greater Chicago - Agreement for Professional Development Program for Management Development and IT (Years 2025–2027) | E82: Metropolitan Water Reclamation District of Greater Chicago | F82: Chicago | G82: Closed Won | H82: Yes | I82: Interview | J82: 46160 | L82: 18620 | M82: Training | O82: Madhav Mitruka | P82: Interview Scheduled | Q82: 2025-08-28 | S82: 2026-01-08 | U82: 46098 | V82: In Process | Y82: 2025-08-11 | Z82: https://app.hubspot.com/contacts/243046792/record/0-3/140123456196 | AA82: Yes
A83: 89 | B83: 261982669555 | D83: Madison Metropolitan Sewerage District - IT Backfill for ERP Configuration (SOW 2) | E83: Madison Metropolitan Sewerage District | F83: Wisconsin | G83: Closed Won | H83: No | J83: 46006 | K83: 46048 | L83: 157000 | M83: Staff Augmentation | O83: Amber Soni | S83: 2025-10-24 | U83: 46037 | V83: In Process | Y83: 2026-01-14 | Z83: https://app.hubspot.com/contacts/243046792/record/0-3/261982669555 | AA83: Yes
A84: 91 | B84: 328510794433 | D84: Madison Metropolitan Sewerage District - Workday BA - (SOW 4) | E84: Madison Metropolitan Sewerage District | F84: Wisconsin | G84: Closed Won | H84: No | J84: 46184 | K84: 46184 | L84: 170560 | M84: Managed Services (MSP);Staff Augmentation | O84: Amber Soni | S84: 46184 | Y84: 46178 | Z84: https://app.hubspot.com/contacts/243046792/record/0-3/328510794433
A85: 92 | B85: 254846547704 | D85: City of Portland, Bureau of Technology Services (BTS) - BTS On-Call Services - PRODUCT MANAGEMENT SERVICES | E85: City of Portland, Bureau of Technology Services (BTS) | F85: Maine | G85: Closed Won | J85: 46204 | K85: 46008 | M85: Consulting | O85: Madhav Mitruka | S85: 46176 | Y85: 46027 | Z85: https://app.hubspot.com/contacts/243046792/record/0-3/254846547704
A86: 93 | B86: 173703980764 | D86: Belton Independent School District - Software & Applications | E86: Belton Independent School District ( District ) | F86: Texas | G86: Closed Won | J86: 46219 | K86: 45981 | M86: Reseller | O86: Jyothsna Nanda kishore | Y86: 45931 | Z86: https://app.hubspot.com/contacts/243046792/record/0-3/173703980764
A87: 94 | B87: 331477789421 | D87: Collier County - OPENCollier MPO WordPress Website Maintenance & Hosting - Renewal - 2026 Renewal | E87: Collier County | F87: Florida | G87: Closed Won | J87: 46296 | K87: 46192 | L87: 4630 | M87: Managed Services (MSP);Consulting | O87: Ashutosh Chauhan | S87: 46204 | U87: 46204 | Y87: 46192 | Z87: https://app.hubspot.com/contacts/243046792/record/0-3/331477789421
A88: 95 | B88: 318929810149 | D88: First 5 Kids Santa Clara County - Outsourced IT Services | E88: First 5 Kids Santa Clara County | F88: California | G88: Closed Won | J88: 46230 | K88: 46129 | L88: 139800 | M88: Managed Services (MSP) | O88: Jyothsna Nanda kishore | S88: 46211 | U88: 46235 | Y88: 46114 | Z88: https://app.hubspot.com/contacts/243046792/record/0-3/318929810149
A89: 96 | B89: 317911783129 | D89: Palm Beach County Housing Authority - Information Technology (IT) Managed Services | E89: Palm Beach County Housing Authority | F89: Florida | G89: Closed Won | J89: 46244 | K89: 46153 | L89: 493500 | M89: Managed Services (MSP) | O89: Ashutosh Chauhan | S89: 46213 | U89: 46240 | Y89: 46107 | Z89: https://app.hubspot.com/contacts/243046792/record/0-3/317911783129
A90: 97 | B90: 329946865354 | D90: Jacksonville Electric Authority (JEA), City of Jacksonville - IT/OT Communications Assessment | E90: JEA | F90: Florida | G90: Closed Won | J90: 46248 | K90: 46210 | M90: Audits and Assessment | O90: Yash More | S90: 46240 | U90: 46247 | Y90: 46188 | Z90: https://app.hubspot.com/contacts/243046792/record/0-3/329946865354
A91: 98 | B91: 344949853888 | D91: Madison Metropolitan Sewerage District - Workday Solutions Architect Services - SOW 5 | E91: Madison Metropolitan Sewerage District | F91: Wisconsin | G91: Closed Won | J91: 46265 | K91: 46258 | L91: 347746.43 | M91: Managed Services (MSP);Staff Augmentation | O91: Amber Soni | S91: 46265 | Y91: 46265 | Z91: https://app.hubspot.com/contacts/243046792/record/0-3/344949853888
A92: 99 | B92: 344730713824 | D92: Madison Metropolitan Sewerage District - Workday Business Analyst Services - SOW 6 | E92: Madison Metropolitan Sewerage District | F92: Wisconsin | G92: Closed Won | K92: 46265 | L92: 153584.52 | M92: Managed Services (MSP);Staff Augmentation | O92: Amber Soni | S92: 46265 | Y92: 46265 | Z92: https://app.hubspot.com/contacts/243046792/record/0-3/344730713824
A93: 100 | B93: 337552991947 | D93: ServiceNow Virtual Agent Implementation | E93: Minnesota Judicial Branch | F93: Minnesota | G93: Closed Won | J93: 46265 | K93: 46237 | L93: 68000 | M93: Staff Augmentation | O93: Yash More | U93: 46254 | Y93: 46226 | Z93: https://app.hubspot.com/contacts/243046792/record/0-3/337552991947
A94: 101 | B94: 332610669272 | D94: City of Cleveland - Software Maintenance | E94: City of Cleveland | F94: Ohio | G94: Closed Won | J94: 46268 | K94: 46202 | L94: 17600 | M94: Reseller | O94: Yash More | S94: 46226 | U94: 46226 | Y94: 46199 | Z94: https://app.hubspot.com/contacts/243046792/record/0-3/332610669272
A95: 102 | B95: 323231105770 | D95: Consulting and Professional Services Master Agreement (CAPSMA) | E95: Los Angeles County - Board of Supervisors | F95: California | G95: Intent to Award | J95: 46290 | K95: 46142 | M95: Consulting | O95: Jyothsna Nanda kishore | S95: 46296 | Y95: 46143 | Z95: https://app.hubspot.com/contacts/243046792/record/0-3/323231105770
A96: 103 | B96: 326366112465 | D96: Superior Court of California, County of Ventura - Microsoft Licensing | E96: SUPERIOR COURT OF CALFORNIA - COUNTY OF VENTURA | F96: California | G96: Closed Won | J96: 46289 | K96: 46178 | L96: 885500 | M96: Consulting;Reseller | O96: Savya Atrey | S96: 46203 | U96: 46203 | Y96: 46170 | Z96: https://app.hubspot.com/contacts/243046792/record/0-3/326366112465
A97: 104 | B97: 327055384298 | D97: Madison Metropolitan Sewerage District - QA Tester - SOW 3 | E97: Madison Metropolitan Sewerage District | F97: Wisconsin | G97: Closed Won | L97: 134400 | M97: Managed Services (MSP) | O97: Amber Soni | U97: 46118 | Z97: https://app.hubspot.com/contacts/243046792/record/0-3/327055384298
A98: 106 | B98: 343611945708 | D98: Cisco End User Quote | E98: New Mexico Finance Authority (“NMFA”) | F98: New Mexico | G98: Intent to Award | J98: 46255 | K98: 46255 | L98: 916.69 | M98: Reseller | O98: Ashutosh Chauhan | S98: 46280 | Z98: https://app.hubspot.com/contacts/243046792/record/0-3/343611945708
A99: 107 | B99: 340785869529 | D99: Case Management System (CMS) Modernization Technical Assistance | E99: San Diego County | F99: California | G99: Intent to Award | J99: 46252 | L99: 209000 | M99: Modernization / Migration | O99: Ashutosh Chauhan | S99: 46280 | Z99: https://app.hubspot.com/contacts/243046792/record/0-3/340785869529
A100: 108 | B100: 335867277022 | D100: State of North Dakota - Health Information Technology Consultant | E100: North Dakota Department of Health and Human Services Rural Health Transformation Program (RHTP) | G100: Intent to Award | J100: 46230 | K100: 46230 | L100: 259400 | M100: Consulting | O100: Jyothsna Nanda kishore | S100: 46266 | Z100: https://app.hubspot.com/contacts/243046792/record/0-3/335867277022
...
